{
  "title": "숭실대학교 일어일문학과 공지사항",
  "source": "https://japanstu.ssu.ac.kr/%ed%95%99%ea%b3%bc%ec%82%ac%eb%ac%b4%ec%8b%a4%ec%95%8c%eb%a6%bc/%ea%b3%b5%ec%a7%80%ec%82%ac%ed%95%ad",
  "description": "숭실대학교 일어일문학과 홈페이지의 공지사항을 제공합니다.",
  "items": [
    {
      "id": "5464",
      "url": "https://japanstu.ssu.ac.kr/%ed%95%99%ea%b3%bc%ec%82%ac%eb%ac%b4%ec%8b%a4%ec%95%8c%eb%a6%bc/%ea%b3%b5%ec%a7%80%ec%82%ac%ed%95%ad/?term_id&slug=5464",
      "author": null,
      "title": "[안내] 2025-1학기 학과근로장학생 모집공고",
      "description": null,
      "category": [
        "공지"
      ],
      "created_at": "2025-01-23T00:00:00+09:00",
      "updated_at": null,
      "thumbnail": null,
      "content": "\n\t\t\t\t\t\t<p><b>2025</b><b>학년도 </b><b>1</b><b>학기 학과근로장학생 모집 안내</b></p>\n<p>&nbsp;</p>\n<p>&nbsp;</p>\n<p>2025학년도 1학기 학과근로장학생을 다음과 같이 모집하니 많은 지원 바랍니다.</p>\n<p>&nbsp;</p>\n<ol>\n<li><b> </b><b>근로장학생 자격 및 선발기준</b></li>\n</ol>\n<p>가. 2025학년도 1학기 국가장학금을 <u><b>1</b></u><u><b>차</b></u> 신청하고 소득분위가 <u><b>9</b></u><u><b>분위 이내인 자</b></u></p>\n<p>※ 국가장학금을 신청할 수 없는 대한민국 국적 미소지자도 선발 가능</p>\n<p>(단, 순수외국인전형으로 입학한 외국인 유학생은 선발 불가)</p>\n<p>나. 2025학년도 1학기 재학 및 복학예정자로 해당학기 등록금 납부 예정인 자</p>\n<p>1) 2025학년도 1학기 전 등록휴학 후 복학시 선발 불가(등록대체자)</p>\n<p>2) 학기 중 미등록, 입학취소, 복학취소 등으로 인한 학적변동시 모든 장학금 취소</p>\n<p>3) 2025학년도 1학기 기준 <u><b>이수학기가 </b></u><u><b>2~7</b></u><u><b>학기만 가능</b></u><u><b>(</b></u><u><b>건축학 전공은 </b></u><u><b>9</b></u><u><b>학기까지</b></u><u><b>)</b></u></p>\n<p><b>※ </b><b>마지막학기 재학생은 선발 불가</b></p>\n<p>다. 직전학기 취득학점 및 학업성적 제한 없음</p>\n<p>라. 타 장학금과 중복수혜 가능(근로장학금 간 중복 불가)</p>\n<p>※ 본 장학금은 학업장려비 지원 목적으로 등록금(입학금 및 수업료)를 초과하여 지급</p>\n<p>마. 국가근로장학생 및 교내근로장학생에 선발되지 않은 자</p>\n<p>※ <u><b>국가근로 및 교내근로 선발자가 포기 후 학과근로 선발될 수 없음</b></u></p>\n<p>&nbsp;</p>\n<ol start=\"2\">\n<li><b> </b><b>근로장학생 종류별 장학금액 및 근로시간</b></li>\n</ol>\n<table>\n<tbody>\n<tr>\n<td>장학금명</td>\n<td>&nbsp;시간당 장학금</td>\n<td>총 근로시간&nbsp;(학기)</td>\n<td>1인당 장학금액(원)</td>\n</tr>\n<tr>\n<td>&nbsp;학과근로A</td>\n<td>10,030원</td>\n<td>10시간*20주=200시간</td>\n<td>2,006,000</td>\n</tr>\n<tr>\n<td>&nbsp;학과근로B</td>\n<td>&nbsp;10,030원</td>\n<td>&nbsp;5시간*20주=100시간</td>\n<td>1,003,000</td>\n</tr>\n</tbody>\n</table>\n<p>※ 일어일문학과는 학과근로A만 선발</p>\n<p>※&nbsp;장학금은 매월 지급하며,&nbsp;실 지급액은 근로시간에 따라 달라질 수 있음</p>\n<p>※ 주 기준은 학기당 받을 수 있는 장학금액 산정을 위한 것이며, 총 시간 내에서 8월까지</p>\n<p>근로할 수 있음</p>\n<p>※ 장학금 지급일: 매월 셋째주 금요일 예정(Ex. 9월분 근로장학금 지급일: 10월 셋째주 금요일)</p>\n<p>&nbsp;</p>\n<ol start=\"3\">\n<li><b></b><b>유의 사항</b></li>\n</ol>\n<p>가. 선발된 학생은 소속부서에서 지정된 근로시간 동안 근무해야 하며, 학기 중 학적변동</p>\n<p>(휴학,&nbsp;자퇴,&nbsp;제적 등)&nbsp;등 불가피한 사유가 인정되는 중도 포기 시 근로 시간 만큼 지급</p>\n<p>나. 2025년 7월 근로평가 전까지 교체 가능(단, 교체 전 학생의 근로시간을 차감)</p>\n<p>다. <b>국가근로 및 교내근로로 선발 시 학과근로 선발에서 제외됨</b></p>\n<p>(선발 우선순위: 1.&nbsp;국가근로, 2.&nbsp;교내근로, 3.&nbsp;학과근로)</p>\n<p>–</p>\n<ol start=\"4\">\n<li><b></b><b>신청절차</b></li>\n</ol>\n<p>가. 학생신청방법: u-SAINT포털 → 등록/장학 → 장학메뉴 ‘근로장학금’→학과근로A 신청 →&nbsp;지원서 출력&nbsp;→&nbsp;지원서&nbsp;제출</p>\n<p><u><b>&nbsp;</b></u><u><b>※ </b></u><u><b>u-SAINT</b></u><u><b>출력본 제출 필수</b></u></p>\n<p>나. 온라인접수 및 서류제출기간: <b>2025</b><b>년 </b><b>2</b><b>월 </b><b>3</b><b>일</b><b>(</b><b>월</b><b>) 10:00 ~ 2</b><b>월 </b><b>7</b><b>일</b><b>(</b><b>금</b><b>) 17:00</b></p>\n<p><b>※ </b><b>제출 일시 이후 제출본은 불인정하니 유의</b></p>\n<p>1)&nbsp;제출서류:&nbsp;지원서(u-SAINT출력본)</p>\n<p>2)&nbsp;제출장소:&nbsp;각 학과사무실</p>\n<p>–</p>\n<ol start=\"5\">\n<li><b></b><b>선발결과 발표</b><b>: </b>2025년 2월 24일(월) 18:00 이후 본교 홈페이지 공지사항 공지 예정</li>\n</ol>\n<p>&nbsp;</p>\n<ol start=\"6\">\n<li><b></b><b>문의</b><b>:&nbsp;</b><b>일어일문학과 사무실(전화번호: 820-0530)</b><b></b></li>\n</ol>\n\t\t\t\t\t",
      "attachments": [],
      "metadata": null
    },
    {
      "id": "5456",
      "url": "https://japanstu.ssu.ac.kr/%ed%95%99%ea%b3%bc%ec%82%ac%eb%ac%b4%ec%8b%a4%ec%95%8c%eb%a6%bc/%ea%b3%b5%ec%a7%80%ec%82%ac%ed%95%ad/?term_id&slug=5456",
      "author": null,
      "title": "[안내] 2025학년도 국내대학 학점교류 실시 및 신청 안내",
      "description": null,
      "category": [],
      "created_at": "2025-01-14T00:00:00+09:00",
      "updated_at": null,
      "thumbnail": null,
      "content": "\n\t\t\t\t\t\t<p><a href=\"https://japanstu.ssu.ac.kr/board/%ec%95%88%eb%82%b4-2025%ed%95%99%eb%85%84%eb%8f%84-%ea%b5%ad%eb%82%b4%eb%8c%80%ed%95%99-%ed%95%99%ec%a0%90%ea%b5%90%eb%a5%98-%ec%8b%a4%ec%8b%9c-%eb%b0%8f-%ec%8b%a0%ec%b2%ad-%ec%95%88%eb%82%b4/4-%ed%99%88%ed%8e%98%ec%9d%b4%ec%a7%80%ea%b3%b5%ec%a7%80-2025%ed%95%99%eb%85%84%eb%8f%84-1%ed%95%99%ea%b8%b0-%ea%b5%ad%eb%82%b4%eb%8c%80%ed%95%99-%ed%95%99%ec%a0%90%ea%b5%90%eb%a5%98-%ec%8b%a0/\" rel=\"attachment wp-att-5457\"><img alt=\"\" class=\"aligncenter size-full wp-image-5457\" height=\"1121\" sizes=\"(max-width: 793px) 100vw, 793px\" src=\"https://japanstu.ssu.ac.kr/wp-content/uploads/sites/119/2025/01/4.-홈페이지공지-2025학년도-1학기-국내대학-학점교류-신청-안내.pdf_page_1.jpg\" srcset=\"https://japanstu.ssu.ac.kr/wp-content/uploads/sites/119/2025/01/4.-홈페이지공지-2025학년도-1학기-국내대학-학점교류-신청-안내.pdf_page_1.jpg 793w, https://japanstu.ssu.ac.kr/wp-content/uploads/sites/119/2025/01/4.-홈페이지공지-2025학년도-1학기-국내대학-학점교류-신청-안내.pdf_page_1-212x300.jpg 212w, https://japanstu.ssu.ac.kr/wp-content/uploads/sites/119/2025/01/4.-홈페이지공지-2025학년도-1학기-국내대학-학점교류-신청-안내.pdf_page_1-768x1086.jpg 768w, https://japanstu.ssu.ac.kr/wp-content/uploads/sites/119/2025/01/4.-홈페이지공지-2025학년도-1학기-국내대학-학점교류-신청-안내.pdf_page_1-724x1024.jpg 724w\" width=\"793\"></a><a href=\"https://japanstu.ssu.ac.kr/board/%ec%95%88%eb%82%b4-2025%ed%95%99%eb%85%84%eb%8f%84-%ea%b5%ad%eb%82%b4%eb%8c%80%ed%95%99-%ed%95%99%ec%a0%90%ea%b5%90%eb%a5%98-%ec%8b%a4%ec%8b%9c-%eb%b0%8f-%ec%8b%a0%ec%b2%ad-%ec%95%88%eb%82%b4/4-%ed%99%88%ed%8e%98%ec%9d%b4%ec%a7%80%ea%b3%b5%ec%a7%80-2025%ed%95%99%eb%85%84%eb%8f%84-1%ed%95%99%ea%b8%b0-%ea%b5%ad%eb%82%b4%eb%8c%80%ed%95%99-%ed%95%99%ec%a0%90%ea%b5%90%eb%a5%98-%ec%8b%a0-2/\" rel=\"attachment wp-att-5458\"><img alt=\"\" class=\"aligncenter size-full wp-image-5458\" height=\"1121\" sizes=\"(max-width: 793px) 100vw, 793px\" src=\"https://japanstu.ssu.ac.kr/wp-content/uploads/sites/119/2025/01/4.-홈페이지공지-2025학년도-1학기-국내대학-학점교류-신청-안내.pdf_page_2.jpg\" srcset=\"https://japanstu.ssu.ac.kr/wp-content/uploads/sites/119/2025/01/4.-홈페이지공지-2025학년도-1학기-국내대학-학점교류-신청-안내.pdf_page_2.jpg 793w, https://japanstu.ssu.ac.kr/wp-content/uploads/sites/119/2025/01/4.-홈페이지공지-2025학년도-1학기-국내대학-학점교류-신청-안내.pdf_page_2-212x300.jpg 212w, https://japanstu.ssu.ac.kr/wp-content/uploads/sites/119/2025/01/4.-홈페이지공지-2025학년도-1학기-국내대학-학점교류-신청-안내.pdf_page_2-768x1086.jpg 768w, https://japanstu.ssu.ac.kr/wp-content/uploads/sites/119/2025/01/4.-홈페이지공지-2025학년도-1학기-국내대학-학점교류-신청-안내.pdf_page_2-724x1024.jpg 724w\" width=\"793\"></a></p>\n<p><b>1. 신청 자격</b></p>\n<p>가. 2025학년도 1학기 3~7학기 재학생</p>\n<p>나. 직전 학기까지 학업성적이 총 평점 평균 3.0 이상</p>\n<p>다. 학칙에 의거 징계받은 사실이 없는 자</p>\n<p>&nbsp;</p>\n<p><b>2. 신청 학점</b><span style=\"color: #393939\">:&nbsp;</span><span style=\"color: #0000ff\"><b>최대 수강신청 가능 학점 범위 내</b></span></p>\n<p>&nbsp;</p>\n<p><b>3. 국내 대학 학점교류 진행 방식</b></p>\n<table border=\"1\">\n<tbody>\n<tr>\n<td valign=\"middle\"><b>학생</b></td>\n<td valign=\"middle\">\n<p class=\"0\">\n</p></td>\n<td valign=\"middle\"><b>학과</b></td>\n<td valign=\"middle\">\n<p class=\"0\">\n</p></td>\n<td valign=\"middle\"><b>단과대학</b></td>\n<td valign=\"middle\">\n<p class=\"0\">\n</p></td>\n<td valign=\"middle\"><b>학사팀</b></td>\n</tr>\n<tr>\n<td rowspan=\"2\" valign=\"middle\">학점교류 신청서<br>\n(붙임1) 작성 후<br>\n학과에 제출</td>\n<td valign=\"middle\">▷</td>\n<td valign=\"middle\">학점교류 신청 접수 및 과목 승인<p></p>\n<p>(학과(부)장)</p></td>\n<td rowspan=\"3\" valign=\"middle\">▷</td>\n<td rowspan=\"3\" valign=\"middle\">학과에서 제출한<br>\n서류를 취합하여<br>\n학사팀으로<br>\n공문 송부</td>\n<td rowspan=\"3\" valign=\"middle\">▷</td>\n<td rowspan=\"3\" valign=\"middle\">단과대학 신청<p></p>\n<p>공문 취합,</p>\n<p>학생 온라인 접수</p>\n<p>(LMS) 확인 후<br>\n교류 학교로<br>\n공문 송부</p></td>\n</tr>\n<tr>\n<td valign=\"middle\">◁</td>\n<td valign=\"middle\">학점교류 신청 승인 결과 안내</td>\n</tr>\n<tr>\n<td valign=\"middle\">승인 받은<p></p>\n<p>학점교류 신청서</p>\n<p>소속 학과에 제출,</p>\n<p>온라인 접수(LMS)</p></td>\n<td valign=\"middle\"></td>\n<td valign=\"middle\">학점교류생 명단<p></p>\n<p>(붙임3)을 작성하여<br>\n학생 제출 서류와<br>\n함께 단과대학&nbsp;제출</p></td>\n</tr>\n</tbody>\n</table>\n<p>※&nbsp; 홈페이지▶학사▶학생교류지원▶학점교류 신청하기 게시판에</p>\n<p><b>대학별 실시 계획이 확정되는 대로&nbsp;<u>계속 업데이트</u>&nbsp;예정</b></p>\n\t\t\t\t\t",
      "attachments": [],
      "metadata": null
    },
    {
      "id": "5453",
      "url": "https://japanstu.ssu.ac.kr/%ed%95%99%ea%b3%bc%ec%82%ac%eb%ac%b4%ec%8b%a4%ec%95%8c%eb%a6%bc/%ea%b3%b5%ec%a7%80%ec%82%ac%ed%95%ad/?term_id&slug=5453",
      "author": null,
      "title": "2025학년도 1학기 백마성적우수장학금 선발기준 안내",
      "description": null,
      "category": [
        "공지"
      ],
      "created_at": "2025-01-13T00:00:00+09:00",
      "updated_at": null,
      "thumbnail": null,
      "content": "\n\t\t\t\t\t\t<p>[자격요건]</p>\n<p>가. 2025학년도 1학기 국가장학금을 신청하여 소득분위 조회가 가능한 자</p>\n<p>1) 국가장학금 1차 신청자에 한하여 등록금고지서 사전감면</p>\n<p>2) 1차 미신청자: 2차 신청/서류제출 확인 후 지급</p>\n<p>(2차 신청자 중 한국장학재단&nbsp;구제신청 시 사후지급)</p>\n<p>3) 국가장학금을 신청할 수 없는 대한민국 국적 미소지자도 선발 가능</p>\n<p>(단, 순수외국인전형으로 입학한 외국인유학생은 선발 불가)</p>\n<p>나. 2025학년도 1학기 재학 및 복학 예정자로 해당 학기 등록금 납부 예정인 자</p>\n<p>1) 2025학년도 1학기 前 등록휴학 후 복학 시 선발 대상에서 제외(등록대체자)</p>\n<p>2) 학기 중 미등록, 입학취소, 복학취소 등으로 인한 학적변동 시 모든 장학금 취소</p>\n<p>3) 선발 후, 학기 중 휴학 시 백마성적우수장학금은 복학 학기로 이월</p>\n<p>※ 추가 또는 교체 선발 시 재학 중인 학생만 선발 가능(휴학생에 대한 추가/교체 불가)</p>\n<p>다. 직전 학기 15학점 이상 이수한 자(졸업 직전학기는 직전학기 12학점 이상)</p>\n<p>라. 2025-1학기가 정규등록학기 8학기 이내인 자(건축학과 건축학전공: 정규등록 10학</p>\n<p>기&nbsp;이내인 자)</p>\n<p>마. F학점 포함 학적부성적 기준 직전 학기&nbsp;<u><b>3.8 이상</b></u>인 자</p>\n<p>바. 모든 교내장학금간 중복수혜 불가</p>\n<p>1) 신청장학금 중 수혜금액이 큰 장학금으로 자동 선발</p>\n<p>2) 중복수혜 가능 장학금: 국가장학금, 교외장학금, 학과우수장학금, 기타 학업장려비 지원 목적 장학금 등</p>\n<p>사. 졸업예정자 선발 불가(조기졸업 대상자 포함)하므로 유의</p>\n<p>&nbsp;</p>\n<p>또한 다음과 같은 학과 내규에 따라 장학금이 지급되오니 참고하시기 바랍니다.</p>\n<p>1) 1학년 재학생은 전공기초와 전공선택 과목을 전부 이수해야 함.</p>\n<p>2) 2,3학년 재학생은 전공선택 3과목 이상 이수해야 함.</p>\n<p>3) 4학년 재학생은 전공선택 2과목 이상 이수해야 함.</p>\n<p>4) 전과를 신청한 학생은 백마 성적 장학금 선발 대상에서 제외됨.</p>\n<p style=\"text-align: center\">\n</p><p style=\"text-align: center\">2025.01.13</p>\n<p style=\"text-align: center\">일어일문학과</p>\n\t\t\t\t\t",
      "attachments": [],
      "metadata": null
    },
    {
      "id": "5442",
      "url": "https://japanstu.ssu.ac.kr/%ed%95%99%ea%b3%bc%ec%82%ac%eb%ac%b4%ec%8b%a4%ec%95%8c%eb%a6%bc/%ea%b3%b5%ec%a7%80%ec%82%ac%ed%95%ad/?term_id&slug=5442",
      "author": null,
      "title": "[안내] 24년도 동계방학 AI기반 맞춤형 학습지원(슈터디) 운영 안내",
      "description": null,
      "category": [],
      "created_at": "2025-01-08T00:00:00+09:00",
      "updated_at": null,
      "thumbnail": null,
      "content": "\n\t\t\t\t\t\t<p><a href=\"https://japanstu.ssu.ac.kr/board/%ec%95%88%eb%82%b4-24%eb%85%84%eb%8f%84-%eb%8f%99%ea%b3%84%eb%b0%a9%ed%95%99-ai%ea%b8%b0%eb%b0%98-%eb%a7%9e%ec%b6%a4%ed%98%95-%ed%95%99%ec%8a%b5%ec%a7%80%ec%9b%90%ec%8a%88%ed%84%b0%eb%94%94/%eb%b6%99%ec%9e%841-1-%ec%8a%88%ed%84%b0%eb%94%94-%ec%84%a4%eb%aa%85%ec%9e%90%eb%a3%8c1/\" rel=\"attachment wp-att-5443\"><img alt=\"\" class=\"aligncenter size-full wp-image-5443\" height=\"3731\" sizes=\"(max-width: 5268px) 100vw, 5268px\" src=\"https://japanstu.ssu.ac.kr/wp-content/uploads/sites/119/2025/01/붙임1-1.-슈터디-설명자료1.jpg\" srcset=\"https://japanstu.ssu.ac.kr/wp-content/uploads/sites/119/2025/01/붙임1-1.-슈터디-설명자료1.jpg 5268w, https://japanstu.ssu.ac.kr/wp-content/uploads/sites/119/2025/01/붙임1-1.-슈터디-설명자료1-300x212.jpg 300w, https://japanstu.ssu.ac.kr/wp-content/uploads/sites/119/2025/01/붙임1-1.-슈터디-설명자료1-768x544.jpg 768w, https://japanstu.ssu.ac.kr/wp-content/uploads/sites/119/2025/01/붙임1-1.-슈터디-설명자료1-1024x725.jpg 1024w\" width=\"5268\"></a><a href=\"https://japanstu.ssu.ac.kr/board/%ec%95%88%eb%82%b4-24%eb%85%84%eb%8f%84-%eb%8f%99%ea%b3%84%eb%b0%a9%ed%95%99-ai%ea%b8%b0%eb%b0%98-%eb%a7%9e%ec%b6%a4%ed%98%95-%ed%95%99%ec%8a%b5%ec%a7%80%ec%9b%90%ec%8a%88%ed%84%b0%eb%94%94/%eb%b6%99%ec%9e%841-2-%ec%8a%88%ed%84%b0%eb%94%94-%ec%84%a4%eb%aa%85%ec%9e%90%eb%a3%8c2/\" rel=\"attachment wp-att-5444\"><img alt=\"\" class=\"aligncenter size-full wp-image-5444\" height=\"3731\" sizes=\"(max-width: 5268px) 100vw, 5268px\" src=\"https://japanstu.ssu.ac.kr/wp-content/uploads/sites/119/2025/01/붙임1-2.-슈터디-설명자료2.jpg\" srcset=\"https://japanstu.ssu.ac.kr/wp-content/uploads/sites/119/2025/01/붙임1-2.-슈터디-설명자료2.jpg 5268w, https://japanstu.ssu.ac.kr/wp-content/uploads/sites/119/2025/01/붙임1-2.-슈터디-설명자료2-300x212.jpg 300w, https://japanstu.ssu.ac.kr/wp-content/uploads/sites/119/2025/01/붙임1-2.-슈터디-설명자료2-768x544.jpg 768w, https://japanstu.ssu.ac.kr/wp-content/uploads/sites/119/2025/01/붙임1-2.-슈터디-설명자료2-1024x725.jpg 1024w\" width=\"5268\"></a></p>\n\t\t\t\t\t",
      "attachments": [],
      "metadata": null
    },
    {
      "id": "5436",
      "url": "https://japanstu.ssu.ac.kr/%ed%95%99%ea%b3%bc%ec%82%ac%eb%ac%b4%ec%8b%a4%ec%95%8c%eb%a6%bc/%ea%b3%b5%ec%a7%80%ec%82%ac%ed%95%ad/?term_id&slug=5436",
      "author": null,
      "title": "숭실대학교 캠퍼스타운 입주기업 모집 홍보",
      "description": null,
      "category": [],
      "created_at": "2024-12-30T00:00:00+09:00",
      "updated_at": null,
      "thumbnail": null,
      "content": "\n\t\t\t\t\t\t<p><a href=\"https://japanstu.ssu.ac.kr/board/%ec%88%ad%ec%8b%a4%eb%8c%80%ed%95%99%ea%b5%90-%ec%ba%a0%ed%8d%bc%ec%8a%a4%ed%83%80%ec%9a%b4-%ec%9e%85%ec%a3%bc%ea%b8%b0%ec%97%85-%eb%aa%a8%ec%a7%91-%ed%99%8d%eb%b3%b4/2024%eb%85%84-%ec%88%ad%ec%8b%a4%eb%8c%80%ed%95%99%ea%b5%90-%ec%ba%a0%ed%8d%bc%ec%8a%a4%ed%83%80%ec%9a%b4-%ec%9e%85%ec%a3%bc%ea%b8%b0%ec%97%85-%eb%aa%a8%ec%a7%91-%ed%99%8d%eb%b3%b4-%ed%8f%ac%ec%8a%a4/\" rel=\"attachment wp-att-5437\"><img alt=\"\" class=\"aligncenter size-full wp-image-5437\" height=\"2818\" sizes=\"(max-width: 1950px) 100vw, 1950px\" src=\"https://japanstu.ssu.ac.kr/wp-content/uploads/sites/119/2024/12/2024년-숭실대학교-캠퍼스타운-입주기업-모집-홍보-포스터.pdf_page_1.jpg\" srcset=\"https://japanstu.ssu.ac.kr/wp-content/uploads/sites/119/2024/12/2024년-숭실대학교-캠퍼스타운-입주기업-모집-홍보-포스터.pdf_page_1.jpg 1950w, https://japanstu.ssu.ac.kr/wp-content/uploads/sites/119/2024/12/2024년-숭실대학교-캠퍼스타운-입주기업-모집-홍보-포스터.pdf_page_1-208x300.jpg 208w, https://japanstu.ssu.ac.kr/wp-content/uploads/sites/119/2024/12/2024년-숭실대학교-캠퍼스타운-입주기업-모집-홍보-포스터.pdf_page_1-768x1110.jpg 768w, https://japanstu.ssu.ac.kr/wp-content/uploads/sites/119/2024/12/2024년-숭실대학교-캠퍼스타운-입주기업-모집-홍보-포스터.pdf_page_1-709x1024.jpg 709w\" width=\"1950\"></a></p>\n\t\t\t\t\t",
      "attachments": [],
      "metadata": null
    },
    {
      "id": "5419",
      "url": "https://japanstu.ssu.ac.kr/%ed%95%99%ea%b3%bc%ec%82%ac%eb%ac%b4%ec%8b%a4%ec%95%8c%eb%a6%bc/%ea%b3%b5%ec%a7%80%ec%82%ac%ed%95%ad/?term_id&slug=5419",
      "author": null,
      "title": "[안내] 2025학년도 수강신청 안내",
      "description": null,
      "category": [
        "공지"
      ],
      "created_at": "2024-12-24T00:00:00+09:00",
      "updated_at": null,
      "thumbnail": null,
      "content": "\n\t\t\t\t\t\t<p><a href=\"https://japanstu.ssu.ac.kr/board/%ec%95%88%eb%82%b4-2025%ed%95%99%eb%85%84%eb%8f%84-%ec%88%98%ea%b0%95%ec%8b%a0%ec%b2%ad-%ec%95%88%eb%82%b4/%ed%99%88%ed%8e%98%ec%9d%b4%ec%a7%80-%ea%b3%b5%ec%a7%80-2025%ed%95%99%eb%85%84%eb%8f%84-1%ed%95%99%ea%b8%b0-%ec%88%98%ea%b0%95%ec%8b%a0%ec%b2%ad-%ec%95%88%eb%82%b4-pdf_page_1-2/\" rel=\"attachment wp-att-5421\"><img alt=\"\" class=\"aligncenter size-full wp-image-5421\" height=\"1121\" sizes=\"(max-width: 793px) 100vw, 793px\" src=\"https://japanstu.ssu.ac.kr/wp-content/uploads/sites/119/2024/12/홈페이지-공지-2025학년도-1학기-수강신청-안내.pdf_page_1-1.jpg\" srcset=\"https://japanstu.ssu.ac.kr/wp-content/uploads/sites/119/2024/12/홈페이지-공지-2025학년도-1학기-수강신청-안내.pdf_page_1-1.jpg 793w, https://japanstu.ssu.ac.kr/wp-content/uploads/sites/119/2024/12/홈페이지-공지-2025학년도-1학기-수강신청-안내.pdf_page_1-1-212x300.jpg 212w, https://japanstu.ssu.ac.kr/wp-content/uploads/sites/119/2024/12/홈페이지-공지-2025학년도-1학기-수강신청-안내.pdf_page_1-1-768x1086.jpg 768w, https://japanstu.ssu.ac.kr/wp-content/uploads/sites/119/2024/12/홈페이지-공지-2025학년도-1학기-수강신청-안내.pdf_page_1-1-724x1024.jpg 724w\" width=\"793\"></a> <a href=\"https://japanstu.ssu.ac.kr/board/%ec%95%88%eb%82%b4-2025%ed%95%99%eb%85%84%eb%8f%84-%ec%88%98%ea%b0%95%ec%8b%a0%ec%b2%ad-%ec%95%88%eb%82%b4/%ed%99%88%ed%8e%98%ec%9d%b4%ec%a7%80-%ea%b3%b5%ec%a7%80-2025%ed%95%99%eb%85%84%eb%8f%84-1%ed%95%99%ea%b8%b0-%ec%88%98%ea%b0%95%ec%8b%a0%ec%b2%ad-%ec%95%88%eb%82%b4-pdf_page_2/\" rel=\"attachment wp-att-5422\"><img alt=\"\" class=\"aligncenter size-full wp-image-5422\" height=\"1121\" sizes=\"(max-width: 793px) 100vw, 793px\" src=\"https://japanstu.ssu.ac.kr/wp-content/uploads/sites/119/2024/12/홈페이지-공지-2025학년도-1학기-수강신청-안내.pdf_page_2.jpg\" srcset=\"https://japanstu.ssu.ac.kr/wp-content/uploads/sites/119/2024/12/홈페이지-공지-2025학년도-1학기-수강신청-안내.pdf_page_2.jpg 793w, https://japanstu.ssu.ac.kr/wp-content/uploads/sites/119/2024/12/홈페이지-공지-2025학년도-1학기-수강신청-안내.pdf_page_2-212x300.jpg 212w, https://japanstu.ssu.ac.kr/wp-content/uploads/sites/119/2024/12/홈페이지-공지-2025학년도-1학기-수강신청-안내.pdf_page_2-768x1086.jpg 768w, https://japanstu.ssu.ac.kr/wp-content/uploads/sites/119/2024/12/홈페이지-공지-2025학년도-1학기-수강신청-안내.pdf_page_2-724x1024.jpg 724w\" width=\"793\"></a> <a href=\"https://japanstu.ssu.ac.kr/board/%ec%95%88%eb%82%b4-2025%ed%95%99%eb%85%84%eb%8f%84-%ec%88%98%ea%b0%95%ec%8b%a0%ec%b2%ad-%ec%95%88%eb%82%b4/%ed%99%88%ed%8e%98%ec%9d%b4%ec%a7%80-%ea%b3%b5%ec%a7%80-2025%ed%95%99%eb%85%84%eb%8f%84-1%ed%95%99%ea%b8%b0-%ec%88%98%ea%b0%95%ec%8b%a0%ec%b2%ad-%ec%95%88%eb%82%b4-pdf_page_3-2/\" rel=\"attachment wp-att-5423\"><img alt=\"\" class=\"aligncenter size-full wp-image-5423\" height=\"1121\" sizes=\"(max-width: 793px) 100vw, 793px\" src=\"https://japanstu.ssu.ac.kr/wp-content/uploads/sites/119/2024/12/홈페이지-공지-2025학년도-1학기-수강신청-안내.pdf_page_3-1.jpg\" srcset=\"https://japanstu.ssu.ac.kr/wp-content/uploads/sites/119/2024/12/홈페이지-공지-2025학년도-1학기-수강신청-안내.pdf_page_3-1.jpg 793w, https://japanstu.ssu.ac.kr/wp-content/uploads/sites/119/2024/12/홈페이지-공지-2025학년도-1학기-수강신청-안내.pdf_page_3-1-212x300.jpg 212w, https://japanstu.ssu.ac.kr/wp-content/uploads/sites/119/2024/12/홈페이지-공지-2025학년도-1학기-수강신청-안내.pdf_page_3-1-768x1086.jpg 768w, https://japanstu.ssu.ac.kr/wp-content/uploads/sites/119/2024/12/홈페이지-공지-2025학년도-1학기-수강신청-안내.pdf_page_3-1-724x1024.jpg 724w\" width=\"793\"></a> <a href=\"https://japanstu.ssu.ac.kr/board/%ec%95%88%eb%82%b4-2025%ed%95%99%eb%85%84%eb%8f%84-%ec%88%98%ea%b0%95%ec%8b%a0%ec%b2%ad-%ec%95%88%eb%82%b4/%ed%99%88%ed%8e%98%ec%9d%b4%ec%a7%80-%ea%b3%b5%ec%a7%80-2025%ed%95%99%eb%85%84%eb%8f%84-1%ed%95%99%ea%b8%b0-%ec%88%98%ea%b0%95%ec%8b%a0%ec%b2%ad-%ec%95%88%eb%82%b4-pdf_page_4-3/\" rel=\"attachment wp-att-5424\"><img alt=\"\" class=\"aligncenter size-full wp-image-5424\" height=\"1121\" sizes=\"(max-width: 793px) 100vw, 793px\" src=\"https://japanstu.ssu.ac.kr/wp-content/uploads/sites/119/2024/12/홈페이지-공지-2025학년도-1학기-수강신청-안내.pdf_page_4-2.jpg\" srcset=\"https://japanstu.ssu.ac.kr/wp-content/uploads/sites/119/2024/12/홈페이지-공지-2025학년도-1학기-수강신청-안내.pdf_page_4-2.jpg 793w, https://japanstu.ssu.ac.kr/wp-content/uploads/sites/119/2024/12/홈페이지-공지-2025학년도-1학기-수강신청-안내.pdf_page_4-2-212x300.jpg 212w, https://japanstu.ssu.ac.kr/wp-content/uploads/sites/119/2024/12/홈페이지-공지-2025학년도-1학기-수강신청-안내.pdf_page_4-2-768x1086.jpg 768w, https://japanstu.ssu.ac.kr/wp-content/uploads/sites/119/2024/12/홈페이지-공지-2025학년도-1학기-수강신청-안내.pdf_page_4-2-724x1024.jpg 724w\" width=\"793\"></a></p>\n\t\t\t\t\t",
      "attachments": [],
      "metadata": null
    },
    {
      "id": "5408",
      "url": "https://japanstu.ssu.ac.kr/%ed%95%99%ea%b3%bc%ec%82%ac%eb%ac%b4%ec%8b%a4%ec%95%8c%eb%a6%bc/%ea%b3%b5%ec%a7%80%ec%82%ac%ed%95%ad/?term_id&slug=5408",
      "author": null,
      "title": "[안내] 2025-1학기 교내장학금 시행 및 신청 안내",
      "description": null,
      "category": [],
      "created_at": "2024-12-23T00:00:00+09:00",
      "updated_at": null,
      "thumbnail": null,
      "content": "\n\t\t\t\t\t\t<p><strong>1. 교내장학금 자격요건</strong></p>\n<p>가. 2025학년도 1학기 국가장학금 신청(1차: 2024.12.26(목) 18:00까지 신청 가능) 및</p>\n<p>서류&nbsp;제출을 완료하고 소득분위가 조회된 자(국가장학금 지급 대상 분위의 경우 심사</p>\n<p>가&nbsp;완료된&nbsp;자)</p>\n<p>나. 2025학년도 1학기 재학 및 복학(예정)자로 등록금 납부 예정인 자</p>\n<p>1) 2025학년도 1학기 前 등록휴학 후 복학 시 장학생 선발대상에서 제외</p>\n<p>2) 미등록, 입학취소, 복학취소, 휴학 등 학적변동 시 모든 장학금 취소</p>\n<p>다. 직전학기 15학점 이상 이수한 자(최종 직전학기는 12학점)</p>\n<p>라. 정규등록학기가 8학기 이내인 자(건축학부 건축학전공은 10학기 이내)</p>\n<p>&nbsp;</p>\n<p><strong>2. 학생 신청절차</strong></p>\n<p>가. 온라인 신청 및 서류제출기간 :&nbsp;<b><u>2024.12.23(월)10:00 ~ 2025.01.10(금)24:00</u></b></p>\n<p>※ 2차: 2025. 03. 03(월)~ 2025. 03. 28(금) 예정</p>\n<p>나. 학생 신청방법: u-SAINT포털 → 등록/장학&nbsp;→&nbsp;장학메뉴&nbsp;→&nbsp;장학금 신청</p>\n<p>다. 학생 서류제출: 온라인 신청기간 내 방문 및 등기우편제출 가능(세부내용 붙임 파일 참</p>\n<p>조)</p>\n<p>※ 단, 전문자격시험합격자장학금의 경우 등기우편 불가</p>\n<p>&nbsp;</p>\n<p><strong>3. 관련 부서 및 협조사항</strong></p>\n<p><strong><u>가. 신청 홍보: 단과대학 교학팀 및 모든 학과(부) – 홈페이지, SNS 등</u></strong></p>\n<p>나. 학생 선발 명단 제출: 아래 부서에만 해당</p>\n<table border=\"1\" cellpadding=\"0\" cellspacing=\"0\">\n<tbody>\n<tr>\n<td><b>&nbsp;장학금명</b></td>\n<td><b>관련부서</b></td>\n<td><b>협조사항</b></td>\n</tr>\n<tr>\n<td>&nbsp;국제교류장학금</td>\n<td>국제교류·유치팀</td>\n<td rowspan=\"5\">1. 온라인 신청없음 (학생문의응대 협조)<br>\n2.&nbsp;부서 장학생 자격 검증 및 해당 장학생 추천&nbsp;3. 기간 내 국가장학금 신청 독려</td>\n</tr>\n<tr>\n<td>&nbsp;특기자장학금(축구)</td>\n<td>학생서비스팀</td>\n</tr>\n<tr>\n<td>&nbsp;특기자장학금<br>\n(골프,당구)</td>\n<td>스포츠학부</td>\n</tr>\n<tr>\n<td>&nbsp;장애학생장학금</td>\n<td>장애학생지원센터</td>\n</tr>\n<tr>\n<td>자립준비청년장학금</td>\n<td>사회공헌팀</td>\n</tr>\n<tr>\n<td>목사자녀장학금</td>\n<td>학원선교팀</td>\n<td rowspan=\"2\">1. 학생문의응대 협조<br>\n2.&nbsp;신청서류 자격 검증 및 해당&nbsp;장학생 추천<br>\n3. 기간 내 국가장학금 신청 독려</td>\n</tr>\n<tr>\n<td>&nbsp;전문자격시험합격자<br>\n장학금</td>\n<td>진로취업센터</td>\n</tr>\n<tr>\n<td>&nbsp;봉사장학금</td>\n<td>봉사장학금<br>\n추천 전 부서</td>\n<td>1. 대상자 기간 내 국가장학금 신청 독려<br>\n2. 기타 봉사장학금 자격 요건 미리 확인하도록 예정자에게 사전&nbsp;안내 요망<br>\n-평점평균 : 2.3 이상<br>\n-학기말까지 임기를 완료한 자 등</td>\n</tr>\n</tbody>\n</table>\n<p><u><strong>다. 장학생 추천&nbsp;기한:&nbsp;2025.01.17(금)까지 공문발송(등록금 고지서 반영 일정 관</strong></u></p>\n<p><strong>&nbsp; &nbsp; &nbsp; &nbsp; &nbsp; &nbsp; &nbsp; &nbsp; &nbsp; &nbsp; &nbsp;&nbsp;계</strong><strong>로, 기</strong><strong>한 준수 요망)</strong></p>\n\t\t\t\t\t",
      "attachments": [],
      "metadata": null
    },
    {
      "id": "5359",
      "url": "https://japanstu.ssu.ac.kr/%ed%95%99%ea%b3%bc%ec%82%ac%eb%ac%b4%ec%8b%a4%ec%95%8c%eb%a6%bc/%ea%b3%b5%ec%a7%80%ec%82%ac%ed%95%ad/?term_id&slug=5359",
      "author": null,
      "title": "[안내]2024학년도 한나장학생 모집 안내(~11/4)",
      "description": null,
      "category": [
        "공지"
      ],
      "created_at": "2024-10-14T00:00:00+09:00",
      "updated_at": null,
      "thumbnail": null,
      "content": "\n\t\t\t\t\t\t<p>2024학년도 한나장학생 모집 안내</p>\n<p>한나장학금은 우리 학과 겸임교수를 역임하신 김정희 교수님께서 출연해 주신 기금으로 운영하는 일어일문학과 내부 장학금입니다.</p>\n<p>조금이나마 학업 수행에 도움이 되었으면 합니다. 많은 지원 바랍니다.</p>\n<p>&nbsp;</p>\n<p>1, 대상: 일어일문학과 1학년</p>\n<p>2. 모집인원: 2명</p>\n<p>3.&nbsp; 구비서류: 자기소개서, 주민등록등본 각 1부</p>\n<p>4. 신청기한: 11월 4일(월) 15시까지 학과사무실로 직접 제출 혹은 이메일(japanstu@ssu.ac.kr) 제출</p>\n<p>5. 장학금액: 1,000,000원(1인당)</p>\n<p>6. 지급시기: 11월 중 예정</p>\n<p>7. 유의사항: 전과, 자퇴 시 수령한 장학금을 반환해야 함.</p>\n<p>8. 기타 문의사항은 학과 사무실(02-820-0530)로 연락 바랍니다.</p>\n\t\t\t\t\t",
      "attachments": [],
      "metadata": null
    },
    {
      "id": "5353",
      "url": "https://japanstu.ssu.ac.kr/%ed%95%99%ea%b3%bc%ec%82%ac%eb%ac%b4%ec%8b%a4%ec%95%8c%eb%a6%bc/%ea%b3%b5%ec%a7%80%ec%82%ac%ed%95%ad/?term_id&slug=5353",
      "author": null,
      "title": "[졸업]2024-2학기 졸업 대체 자격증 및 졸업 논문 계획서 제출 안내",
      "description": null,
      "category": [
        "공지"
      ],
      "created_at": "2024-09-19T00:00:00+09:00",
      "updated_at": null,
      "thumbnail": null,
      "content": "\n\t\t\t\t\t\t<p>2024-2학기 졸업 예정자분들은 기한 내 졸업 대체 자격증 혹은 졸업논문을 제출하여 주시기 바랍니다.</p>\n<p>&nbsp;</p>\n<p>졸업 대체 자격증</p>\n<p>-JPT 700점 이상(제출일 기준으로 2년내 취득분만 유효) 혹은 JLPT N1 이상(점수가 표기되어 있어야 함.)</p>\n<p><span style=\"color: #000000\">-제출기한은 11월 말</span>까지 이며, 스캔하여 학번, 성함과 함께 학과 이메일(japanstu@ssu.ac.kr)로 제출</p>\n<p>&nbsp;</p>\n<p>졸업논문</p>\n<p>-10/18(금)까지 졸업논문계획서를 지도교수님과 논의 후 작성하여 학과 사무실로 직접 제출</p>\n<p>-논문완본은 11월 말까지 제본하여 1부를 학과 사무실로 직접 제출(소프트, 스프링 제본 둘 다 가능)</p>\n<p>-졸업논문계획서 및 졸업논문 양식은 첨부파일 확인</p>\n<p>&nbsp;</p>\n<p>기타 문의사항은 학과홈페이지 졸업요건 메뉴 혹은 학과사무실(02-820-0530)로 문의</p>\n\t\t\t\t\t",
      "attachments": [],
      "metadata": null
    },
    {
      "id": "5346",
      "url": "https://japanstu.ssu.ac.kr/%ed%95%99%ea%b3%bc%ec%82%ac%eb%ac%b4%ec%8b%a4%ec%95%8c%eb%a6%bc/%ea%b3%b5%ec%a7%80%ec%82%ac%ed%95%ad/?term_id&slug=5346",
      "author": null,
      "title": "[안내]제18회 일본어 스피치 콘테스트 주최 안내",
      "description": null,
      "category": [
        "공지"
      ],
      "created_at": "2024-08-28T00:00:00+09:00",
      "updated_at": null,
      "thumbnail": null,
      "content": "\n\t\t\t\t\t\t<p>제18회 일본어 스피치 콘테스트를 다음과 같이 주최하오니 많은 참여 부탁드립니다.</p>\n<p>*일시: 2024.10.10(목) 16:30~18:30</p>\n<p>*장소: 조만식기념관 209호</p>\n<p>*진행방식: 2~3인이 한 팀을 이루어 한국과 일본에 관한 자유 주제에 관해서 팀원 상호간에 일본어로 토론하는 방식으로 진행(팀당 15~20분 동안 진행)</p>\n<p>*포상</p>\n<p>-최우수상: 장학금 80만원 및 상장</p>\n<p>-우수상: 장학금 60만원 및 상장</p>\n<p>-장려상: 장학금 30만원 및 상장</p>\n<p>&nbsp;</p>\n<p>*신청마감: <span style=\"color: #ff0000\"><strong>~09.13(금) 17:00까지</strong></span></p>\n<p>*신청방법: <strong>팀대표가 신청양식을 작성하여 <span style=\"color: #ff0000\">학과사무실 메일(japanstu@ssu.ac.kr)로 제출</span></strong>(양식을 작성하여 서명 후 PDF파일로 제출)</p>\n\t\t\t\t\t",
      "attachments": [],
      "metadata": null
    },
    {
      "id": "5339",
      "url": "https://japanstu.ssu.ac.kr/%ed%95%99%ea%b3%bc%ec%82%ac%eb%ac%b4%ec%8b%a4%ec%95%8c%eb%a6%bc/%ea%b3%b5%ec%a7%80%ec%82%ac%ed%95%ad/?term_id&slug=5339",
      "author": null,
      "title": "[안내]2024학년도 2학기 한국장학재단 국가장학금 2차 신청 안내(~9/11)",
      "description": null,
      "category": [],
      "created_at": "2024-08-13T00:00:00+09:00",
      "updated_at": null,
      "thumbnail": null,
      "content": "\n\t\t\t\t\t\t<p><a href=\"https://japanstu.ssu.ac.kr/board/%ec%95%88%eb%82%b42024%ed%95%99%eb%85%84%eb%8f%84-2%ed%95%99%ea%b8%b0-%ed%95%9c%ea%b5%ad%ec%9e%a5%ed%95%99%ec%9e%ac%eb%8b%a8-%ea%b5%ad%ea%b0%80%ec%9e%a5%ed%95%99%ea%b8%88-2%ec%b0%a8-%ec%8b%a0/%ea%b5%ad%ea%b0%80%ec%9e%a5%ed%95%99%ea%b8%88/\" rel=\"attachment wp-att-5342\"><img alt=\"\" class=\"aligncenter size-full wp-image-5342\" height=\"1080\" sizes=\"(max-width: 1080px) 100vw, 1080px\" src=\"https://japanstu.ssu.ac.kr/wp-content/uploads/sites/119/2024/08/국가장학금.png\" srcset=\"https://japanstu.ssu.ac.kr/wp-content/uploads/sites/119/2024/08/국가장학금.png 1080w, https://japanstu.ssu.ac.kr/wp-content/uploads/sites/119/2024/08/국가장학금-150x150.png 150w, https://japanstu.ssu.ac.kr/wp-content/uploads/sites/119/2024/08/국가장학금-300x300.png 300w, https://japanstu.ssu.ac.kr/wp-content/uploads/sites/119/2024/08/국가장학금-768x768.png 768w, https://japanstu.ssu.ac.kr/wp-content/uploads/sites/119/2024/08/국가장학금-1024x1024.png 1024w\" width=\"1080\"></a></p>\n\t\t\t\t\t",
      "attachments": [],
      "metadata": null
    },
    {
      "id": "5328",
      "url": "https://japanstu.ssu.ac.kr/%ed%95%99%ea%b3%bc%ec%82%ac%eb%ac%b4%ec%8b%a4%ec%95%8c%eb%a6%bc/%ea%b3%b5%ec%a7%80%ec%82%ac%ed%95%ad/?term_id&slug=5328",
      "author": null,
      "title": "[안내]2024학년도 2학기 학과근로 장학생 선발 시행 안내",
      "description": null,
      "category": [],
      "created_at": "2024-07-29T00:00:00+09:00",
      "updated_at": null,
      "thumbnail": null,
      "content": "\n\t\t\t\t\t\t<p><b>1. 학과근로장학생 자격 및 선발기준</b></p>\n<p>가. 2024학년도 2학기 국가장학금을&nbsp;<strong><u>1차</u></strong>&nbsp;신청(붙임2)하고 소득분위가 8분위 이내인 자</p>\n<p>※ 국가장학금을 신청할 수 없는 대한민국 국적 미소지자도 선발 가능</p>\n<p>(단, 순수외국인전형으로 입학한 외국인 유학생은 선발 불가)</p>\n<p>나. 2024학년도 2학기 재학 및 복학 예정자로 해당 학기 등록금 납부 예정인 자</p>\n<p>1) 2024학년도 2학기 전 등록휴학 후 복학 시 선발 불가(등록대체자)</p>\n<p>2) 학기 중 미등록, 입학취소, 복학취소 등으로 인한 학적변동시 모든 장학금 취소</p>\n<p>3) 2024학년도 2학기 기준 이수학기가&nbsp;<u>2~8학기</u>인 학생만 가능(1학기 신청 불가, 건축학&nbsp;전공자의 경우 10학기까지 신청 가능)</p>\n<p>다. 직전학기 취득학점 및 학업성적 제한 없음</p>\n<p>라. 장애인, 북한이탈주민 및 자립준비청년 우선 선발(한국장학재단 정보 활용)</p>\n<p>마. 타 장학금과 중복수혜 가능(근로장학금 간 중복 불가)</p>\n<p>※ 본 장학금은 학업장려비 지원 목적으로 등록금(수업료)을 초과하여 지급 가능</p>\n<p>바. 학과별 배정인원 내에서 학과근로A 또는 B 타입 학과 자율 선발 가능</p>\n<p>(예: 학과근로B 2명 = 학과근로A 1명)</p>\n<p>사. 국가근로장학생 및 교내근로장학생에 선발되지 않은 자</p>\n<p>&nbsp;</p>\n<p><b>3. 유의사항</b></p>\n<p>가. 선발된 학생은 소속 부서에서 지정된 근로 시간 동안 근무해야 하며, 학기 중 학적변동</p>\n<p>(휴학, 자퇴, 제적 등) 등&nbsp;불가피한 사유가 인정되는 중도 포기 시 근로한 시간만 장학</p>\n<p>금&nbsp;지급</p>\n<p>나. 2024년 12월 근로평가 전까지 교체 가능 (단, 교체 전 학생의 근로시간을 차감)</p>\n<p><b><u>※ 근로 중도 교체 및 중단 시 장학팀으로 공문 요망</u></b></p>\n<p>다. 교체 전·후 학생 모두 근로평가 실시</p>\n<p>&nbsp;</p>\n<p><b>4. 예산사항</b></p>\n<p>가. 시간당 장학금액을 9,860원으로 책정</p>\n<table border=\"1\" cellpadding=\"0\" cellspacing=\"0\">\n<tbody>\n<tr>\n<td>장학금명</td>\n<td>시간당<p></p>\n<p>장학금액</p></td>\n<td>총 근로시간(학기)</td>\n<td>1인당<p></p>\n<p>장학금액(원)</p></td>\n<td>인원(명)</td>\n<td>합계(원)</td>\n</tr>\n<tr>\n<td>교내근로A</td>\n<td>&nbsp;9,860원</td>\n<td>&nbsp;16시간*20주=320시간</td>\n<td>3,155,200</td>\n<td>28</td>\n<td>88,345,600</td>\n</tr>\n<tr>\n<td>학과근로A</td>\n<td>9,860원</td>\n<td>&nbsp;10시간*20주=200시간</td>\n<td>1,972,000</td>\n<td>200</td>\n<td>394,400,000</td>\n</tr>\n<tr>\n<td>학과근로B</td>\n<td>&nbsp;9,860원</td>\n<td>&nbsp;5시간*20주=100시간</td>\n<td>986,000</td>\n<td>0</td>\n<td>0</td>\n</tr>\n<tr>\n<td colspan=\"4\">&nbsp;총계</td>\n<td>&nbsp;&nbsp;228</td>\n<td>482,745,600</td>\n</tr>\n</tbody>\n</table>\n<p>※ 국제무역학과, 금융경제학과, 미디어경영학과&nbsp;배정인원(학과 자체 예산) 미반영</p>\n<p>나.&nbsp;학과근로 A유형을&nbsp;기준으로 배정하며,&nbsp;<strong>학과별로 A:B=1:2 비율로 조정 가능</strong></p>\n<p><b>&nbsp;</b>다. 재원: 교내장학금_학부 / 근로장학_비등</p>\n<p>라. 지급일정:&nbsp;매월 셋째주 금요일</p>\n<p>&nbsp;</p>\n<p><b>5. 행정사항</b></p>\n<p>가. 선발공고: 2024년 7월 31일(수)</p>\n<p>나. 학생신청방법: u-SAINT포털→등록/장학→근로장학금 신청→지원서 출력/제출</p>\n<p>다. 온라인신청 및 서류제출기간: <span style=\"color: #ff0000\"><strong>2024.8.1(목) 10:00 ~ 8. 9(금) 17:00</strong></span></p>\n<p>1) 제출서류: <span style=\"color: #ff0000\"><strong>지원서(u-SAINT 출력본,&nbsp;본인서명 필수)</strong></span></p>\n<p>2) 선발인원: 학과근로A 2명, 학과근로B 2명</p>\n<p>3) 제출장소: 교내근로(장학팀), 학과근로(각 학과사무실)</p>\n<p>라. 교내 및 학과근로장학생 최종선발 및 발표: 2024. 8. 23(금) 18:00 예정</p>\n\t\t\t\t\t",
      "attachments": [],
      "metadata": null
    },
    {
      "id": "5320",
      "url": "https://japanstu.ssu.ac.kr/%ed%95%99%ea%b3%bc%ec%82%ac%eb%ac%b4%ec%8b%a4%ec%95%8c%eb%a6%bc/%ea%b3%b5%ec%a7%80%ec%82%ac%ed%95%ad/?term_id&slug=5320",
      "author": null,
      "title": "2024학년도 2학기 백마성적우수장학금 선발기준 안내",
      "description": null,
      "category": [],
      "created_at": "2024-07-18T00:00:00+09:00",
      "updated_at": null,
      "thumbnail": null,
      "content": "\n\t\t\t\t\t\t<p>5. 자격요건</p>\n<p>가. 2024학년도 2학기 국가장학금을 신청하여 소득분위 조회가 가능한 자</p>\n<p>1) 1차 신청자에 한하여 등록금고지서 사전감면 가능</p>\n<p>2) 1차 미신청자: 2차 신청/서류제출 확인 후 지급</p>\n<p>(2차 신청자 중 한국장학재단 구제신청 시 사후지급)</p>\n<p>3) 국가장학금을 신청할 수 없는 대한민국 국적 미소지자도 선발 가능</p>\n<p>(단, 순수외국인전형으로 입학한 외국인 유학생은 선발 불가)</p>\n<p>나. 2024학년도 2학기 재학 및 복학예정자로 해당학기 등록금 납부 예정인 자</p>\n<p>1) 2024학년도 2학기 前 등록휴학 후 복학 시 선발대상에서 제외(등록대체자)</p>\n<p>2) 학기 중 미등록, 자퇴, 제적,&nbsp;입학취소,&nbsp;복학 취소&nbsp;등&nbsp;학적변동시 모든 장학금 취소</p>\n<p>3)&nbsp;선발 후, 학기 중 휴학 시 백마성적우수장학금은 복학 학기로 이월</p>\n<p><b>&nbsp;</b>&nbsp;–&nbsp;복학 학기에 국가장학금 신청 의무임(해당 사항 학생 안내 요망)</p>\n<p>4) 추가 또는 교체 선발 시에는 재학 중인 학생만 선발 가능(휴학생 추가/교체 불가)</p>\n<p>다. 직전학기 15학점 이상 이수한 자(졸업 직전학기는 직전학기 12학점 이상)</p>\n<p>라. 정규등록학기가 8학기 이내인 자(건축학과 건축학전공: 정규등록 10학기 이내인 자)</p>\n<p>마. F학점 포함 학적부성적 기준 직전 학기 평점평균&nbsp;<u><b>3.8 이상</b></u>인 자</p>\n<p>※ 2024학년도 2학기부터 선발 최소 기준 변경(장학팀-4560(2024.01.09)호와 관련하여</p>\n<p>기 안내사항임)</p>\n<table align=\"center\" border=\"1\" cellpadding=\"0\" cellspacing=\"0\">\n<tbody>\n<tr>\n<td>구분</td>\n<td>변경 전</td>\n<td><b><u>변경 후</u></b></td>\n<td>비고</td>\n</tr>\n<tr>\n<td>평점평균 기준</td>\n<td><b><u>3.5</u></b>/4.5</td>\n<td><b><u>3.8</u></b>/4.5</td>\n<td>2024.2.19.<p></p>\n<p>홈페이지 공지 완료</p></td>\n</tr>\n</tbody>\n</table>\n<p>&nbsp;</p>\n<p>바. 모든 교내장학금간 중복수혜 불가</p>\n<p>1) 신청장학금 중 수혜금액이 큰 장학금 선발</p>\n<p>2) 중복수혜 가능 장학금: 국가장학금, 교외장학금, 학과우수장학금, 기타 학업장려비 지원 목적 장학금 등</p>\n<p>사. 졸업예정자 선발 불가(조기졸업 대상자 포함)하므로 유의</p>\n<p>&nbsp;</p>\n<p>또한 다음과 같은 학과 내규에 따라 장학금이 지급되오니 참고하시기 바랍니다.</p>\n<p>1) 1학년 재학생은 전공기초와 전공선택 과목을 전부 이수해야 함.</p>\n<p>2) 2,3학년 재학생은 전공선택 3과목 이상 이수해야 함.</p>\n<p>3) 4학년 재학생은 전공선택 2과목 이상 이수해야 함.</p>\n<p>4) 전과를 신청한 학생은 백마 성적 장학금 선발 대상에서 제외됨.</p>\n<p>&nbsp;</p>\n<p style=\"text-align: center\">2024.07.18</p>\n<p style=\"text-align: center\">일어일문학과</p>\n\t\t\t\t\t",
      "attachments": [],
      "metadata": null
    },
    {
      "id": "5315",
      "url": "https://japanstu.ssu.ac.kr/%ed%95%99%ea%b3%bc%ec%82%ac%eb%ac%b4%ec%8b%a4%ec%95%8c%eb%a6%bc/%ea%b3%b5%ec%a7%80%ec%82%ac%ed%95%ad/?term_id&slug=5315",
      "author": null,
      "title": "[안내]2024학년도 교직과정 이수 신청 안내",
      "description": null,
      "category": [],
      "created_at": "2024-06-24T00:00:00+09:00",
      "updated_at": null,
      "thumbnail": null,
      "content": "\n\t\t\t\t\t\t<p><b>1. 교직이수 신청기간:&nbsp;2024.6.17.(월) 10:00 ~ 12.6.(금) 23:59</b></p>\n<p>※ 2024-1학기 기준 2학년 2학기(4학기) 재학 중인 학생은&nbsp;<u>2024.8.31.(토) 23:59까지</u></p>\n<p>u-SAINT를 통한 신청 및 적·인성 검사 응시를 완료하여야 함</p>\n<p>&nbsp;</p>\n<p><b>2. 선발대상</b></p>\n<p>가 .교직과정 설치학과(부) 소속&nbsp;<u>2학년(3학기 혹은 4학기) 재학생</u></p>\n<table border=\"1\" cellpadding=\"0\" cellspacing=\"0\">\n<tbody>\n<tr>\n<td style=\"text-align: center\">’24-1학기 기준 학적</td>\n<td style=\"text-align: center\">’24-2학기 기준 학적</td>\n<td style=\"text-align: center\">신청가능 여부</td>\n</tr>\n<tr>\n<td rowspan=\"1\" style=\"text-align: center\">&nbsp;2학년 1학기(3학기) 재학</td>\n<td rowspan=\"1\" style=\"text-align: center\">&nbsp;2학년 1학기(3학기) 재학</td>\n<td colspan=\"1\" rowspan=\"3\" style=\"text-align: center\">신청&nbsp;<b>가능</b></td>\n</tr>\n<tr>\n<td style=\"text-align: center\">&nbsp;2학년 1학기(3학기) 이수 후 휴학</td>\n<td style=\"text-align: center\">&nbsp;2학년 1학기(3학기) 이수 후 휴학</td>\n</tr>\n<tr>\n<td style=\"text-align: center\">&nbsp;2학년 2학기(4학기) 재학</td>\n<td style=\"text-align: center\">&nbsp;2학년 2학기(4학기) 재학</td>\n</tr>\n<tr>\n<td style=\"text-align: center\">&nbsp;2학년 2학기(4학기) 이수 후 휴학</td>\n<td style=\"text-align: center\">&nbsp;2학년 2학기(4학기) 이수 후 휴학</td>\n<td style=\"text-align: center\">신청&nbsp;<b>불가</b></td>\n</tr>\n</tbody>\n</table>\n<p>※ 재입학생 및 편입생은 교직과정 이수&nbsp;<u>불가</u>(예외사항 붙임 안내문 참조)</p>\n<p>&nbsp;</p>\n<p><b>3. 교직과정 설치학과(부)별 선발 인원</b></p>\n<table border=\"1\" cellpadding=\"0\" cellspacing=\"0\">\n<tbody>\n<tr>\n<td style=\"text-align: center\">대학</td>\n<td style=\"text-align: center\">학과(부)</td>\n<td style=\"text-align: center\">표시과목</td>\n<td style=\"text-align: center\">선발인원(명)</td>\n</tr>\n<tr>\n<td colspan=\"1\" rowspan=\"6\" style=\"text-align: center\">인문대학</td>\n<td rowspan=\"1\" style=\"text-align: center\">국어국문학과</td>\n<td rowspan=\"1\" style=\"text-align: center\">국어</td>\n<td rowspan=\"1\" style=\"text-align: center\">3</td>\n</tr>\n<tr>\n<td style=\"text-align: center\">영어영문학과</td>\n<td style=\"text-align: center\">영어</td>\n<td style=\"text-align: center\">7</td>\n</tr>\n<tr>\n<td style=\"text-align: center\">중어중문학과</td>\n<td style=\"text-align: center\">중국어</td>\n<td style=\"text-align: center\">2</td>\n</tr>\n<tr>\n<td style=\"text-align: center\">일어일문학과</td>\n<td style=\"text-align: center\">일본어</td>\n<td style=\"text-align: center\">3</td>\n</tr>\n<tr>\n<td style=\"text-align: center\">철학과</td>\n<td style=\"text-align: center\">철학</td>\n<td style=\"text-align: center\">2</td>\n</tr>\n<tr>\n<td style=\"text-align: center\">사학과</td>\n<td style=\"text-align: center\">역사</td>\n<td style=\"text-align: center\">3</td>\n</tr>\n<tr>\n<td colspan=\"1\" rowspan=\"3\" style=\"text-align: center\">자연과학대학</td>\n<td rowspan=\"1\" style=\"text-align: center\">수학과</td>\n<td rowspan=\"1\" style=\"text-align: center\">수학</td>\n<td rowspan=\"1\" style=\"text-align: center\">3</td>\n</tr>\n<tr>\n<td style=\"text-align: center\">물리학과</td>\n<td style=\"text-align: center\">물리</td>\n<td style=\"text-align: center\">4</td>\n</tr>\n<tr>\n<td style=\"text-align: center\">화학과</td>\n<td style=\"text-align: center\">화학</td>\n<td style=\"text-align: center\">4</td>\n</tr>\n<tr>\n<td colspan=\"1\" rowspan=\"2\" style=\"text-align: center\">경제통상대학</td>\n<td rowspan=\"1\" style=\"text-align: center\">경제학과</td>\n<td rowspan=\"1\" style=\"text-align: center\">일반사회</td>\n<td rowspan=\"1\" style=\"text-align: center\">3</td>\n</tr>\n<tr>\n<td style=\"text-align: center\">글로벌통상학과</td>\n<td style=\"text-align: center\">상업</td>\n<td style=\"text-align: center\">5</td>\n</tr>\n<tr>\n<td colspan=\"1\" rowspan=\"2\" style=\"text-align: center\">경영대학</td>\n<td rowspan=\"1\" style=\"text-align: center\">경영학부</td>\n<td rowspan=\"1\" style=\"text-align: center\">상업</td>\n<td rowspan=\"1\" style=\"text-align: center\">8</td>\n</tr>\n<tr>\n<td style=\"text-align: center\">회계학과</td>\n<td style=\"text-align: center\">상업</td>\n<td style=\"text-align: center\">2</td>\n</tr>\n<tr>\n<td colspan=\"1\" rowspan=\"2\" style=\"text-align: center\">공과대학</td>\n<td rowspan=\"1\" style=\"text-align: center\">화학공학과</td>\n<td rowspan=\"1\" style=\"text-align: center\">화공</td>\n<td rowspan=\"1\" style=\"text-align: center\">3</td>\n</tr>\n<tr>\n<td style=\"text-align: center\">전기공학부</td>\n<td style=\"text-align: center\">전기</td>\n<td style=\"text-align: center\">6</td>\n</tr>\n<tr>\n<td colspan=\"1\" rowspan=\"5\" style=\"text-align: center\">IT대학</td>\n<td colspan=\"1\" rowspan=\"2\" style=\"text-align: center\">전자정보공학부<p></p>\n<p>전자공학전공</p></td>\n<td rowspan=\"1\" style=\"text-align: center\">전자</td>\n<td colspan=\"1\" rowspan=\"2\" style=\"text-align: center\">4</td>\n</tr>\n<tr>\n<td style=\"text-align: center\">통신</td>\n</tr>\n<tr>\n<td colspan=\"1\" rowspan=\"2\" style=\"text-align: center\">전자정보공학부<p></p>\n<p>IT융합전공</p></td>\n<td rowspan=\"1\" style=\"text-align: center\">전자</td>\n<td colspan=\"1\" rowspan=\"2\" style=\"text-align: center\">4</td>\n</tr>\n<tr>\n<td style=\"text-align: center\">통신</td>\n</tr>\n<tr>\n<td style=\"text-align: center\">컴퓨터학부</td>\n<td style=\"text-align: center\">정보·컴퓨터</td>\n<td style=\"text-align: center\">7</td>\n</tr>\n<tr>\n<td colspan=\"3\" rowspan=\"1\" style=\"text-align: center\">계</td>\n<td rowspan=\"1\" style=\"text-align: center\">73</td>\n</tr>\n</tbody>\n</table>\n<p>&nbsp;</p>\n<p><b>4. 학교 홈페이지 공지사항 참조:</b>&nbsp;<a href=\"https://scatch.ssu.ac.kr/vvsp\" target=\"none\" title=\"교직과정 이수 신청 안내\">https://scatch.ssu.ac.kr/vvsp</a></p>\n\t\t\t\t\t",
      "attachments": [],
      "metadata": null
    },
    {
      "id": "5310",
      "url": "https://japanstu.ssu.ac.kr/%ed%95%99%ea%b3%bc%ec%82%ac%eb%ac%b4%ec%8b%a4%ec%95%8c%eb%a6%bc/%ea%b3%b5%ec%a7%80%ec%82%ac%ed%95%ad/?term_id&slug=5310",
      "author": null,
      "title": "[안내]2024학년도 2학기 학·석사연계과정 지원 및 선발 안내",
      "description": null,
      "category": [],
      "created_at": "2024-05-20T00:00:00+09:00",
      "updated_at": null,
      "thumbnail": null,
      "content": "\n\t\t\t\t\t\t<p>2024학년도 2학기 학·석사연계과정 지원 및 선발을 아래와 같이 진행하고자 하니 관심있는 학사과정생들이 지원할 수 있도록 안내하여 주시기 바랍니다.</p>\n<p>&nbsp;</p>\n<p>1. 지원기간 : 2024.06.03(월)~06.14(금)</p>\n<p>&nbsp;</p>\n<p>2. 모집학과 : 학사과정과 석사과정에 동일(또는 유사)학과가 있는 학과(계약학과 제외)</p>\n<p>&nbsp;</p>\n<p>3.지원자격 :&nbsp;<b><u>다음 각호 모두 해당되는 자</u></b></p>\n<p>가. 지원일 당시 학사과정 4학기 이상 6학기 이내 재학 중(건축학부 건축학전공은 6학기 이상 8학기 이내 재학 중)인 자&nbsp;(학·석사연계과정 신청자는 조기졸업 신청을 할 수 없음)</p>\n<p>나. 재수강 이전 과목, 학점포기한 과목, F학점 과목 등을 포함한 전체 과목의&nbsp;총평점평균이 3.0 / 4.5 이상인 자</p>\n<p>다.&nbsp;7학기 또는 8학기(건축학부 건축학 전공은 9학기 또는 10학기)에 학사과정의 졸업요건을 충족할 수 있는 자</p>\n<p>라. 지원하고자 하는 일반대학원 학과 주임교수와 지도교수의 추천을 받은 자</p>\n<p>마. 지원하고자 하는 일반대학원의 동일(또는 유사)학과를 주전공 또는 복수전공으로 하는자</p>\n<p>&nbsp;</p>\n<p>4. 제출서류 및 지원방법</p>\n<p>가. 학·석사연계과정 신청서 1부.</p>\n<p>나. 대학원 교학팀으로 방문 접수(웨스트민스터홀 658호)</p>\n<p>&nbsp;</p>\n<p>5. 선발인원 : 석사과정 입학정원의 20%</p>\n<p>&nbsp;</p>\n<p>6. 발표일 : 2024.07.26(금) 예정 – 학과 및 개별통지</p>\n<p>&nbsp;</p>\n<p>7. 관련안내</p>\n<p>가. 대상 : 지원가능 대상자 및 학과</p>\n<p>나. 방법 : 안내문 배포 및 대학원 홈페이지 공지</p>\n<p>&nbsp;</p>\n<p>8. 문의처 : 대학원 교학팀(02-820.0258~9 , grad@ssu.ac.kr)</p>\n\t\t\t\t\t",
      "attachments": [],
      "metadata": null
    },
    {
      "id": "5297",
      "url": "https://japanstu.ssu.ac.kr/%ed%95%99%ea%b3%bc%ec%82%ac%eb%ac%b4%ec%8b%a4%ec%95%8c%eb%a6%bc/%ea%b3%b5%ec%a7%80%ec%82%ac%ed%95%ad/?term_id&slug=5297",
      "author": null,
      "title": "[안내]2025년도 일본 정부(문부과학성) 장학금 연구유학생 및 일한 공동고등교육 유학생 교류사업(석사, 박사 학위 과정) 선발 안내(~5/13)",
      "description": null,
      "category": [],
      "created_at": "2024-05-02T00:00:00+09:00",
      "updated_at": null,
      "thumbnail": null,
      "content": "\n\t\t\t\t\t\t<p>가. 자격 및 조건</p>\n<p>1) 연령: 1990년 4월 2일 이후 출생한 대한민국 국적 소지자</p>\n<p>2) 학력: 일본의 대학 졸업 또는 졸업예정자와 동등한 자격을 가진 자 등</p>\n<p>3) 장학기간: 원칙적으로 2025년 4월부터 2년간이며, 10월(또는 9월)부터는 1년 6개월간(단, 상위과정 진학시 연장 가능)</p>\n<p>4) 장학금: 학비 및 항공요금 지급 외에 매월 약 143,000엔 지급 등</p>\n<p>나. 지원방법: 지원자가 직접 하단의&nbsp;<b>제출서류를</b><b>2024년 5월 13일(월)</b>까지 주한일본대사관 공보문화원&nbsp;<b>이메일(yuhak@so.mofa.go.jp)로 송부</b></p>\n<p>다. 제출서류: ①연구유학생 응모자 Excel 파일(사진첨부), ②최종 학력의 졸업/졸업예정증명서, ③졸업(수료)예정 확인서, ④일본 재류 기간 등에 대한 확인서, ⑤언어 능력 증명서, ⑥ 퇴역 예정 증명서 &nbsp; ※③,④,⑤,⑥ 은 해당자만 제출</p>\n<p>라.&nbsp;<b>반드시 &lt;붙임 1,2,3&gt; 모집요강 및 모집 절차·일정에서 지원자격, 제출서류 등 세부 사항을 숙지하고 지원</b>하며, 제출 서류 양식은 주한일본대사관 홈페이지 공지사항 및 Study in Japan 홈페이지를 확인할 것</p>\n<p>마.&nbsp;<b>문의처: 주한일본대사관 공보문화원</b></p>\n<p>(전화 02-765-3011~3 &lt;내선 144,145&gt;, 이메일: yuhak@so.mofa.go.jp)</p>\n\t\t\t\t\t",
      "attachments": [],
      "metadata": null
    },
    {
      "id": "5282",
      "url": "https://japanstu.ssu.ac.kr/%ed%95%99%ea%b3%bc%ec%82%ac%eb%ac%b4%ec%8b%a4%ec%95%8c%eb%a6%bc/%ea%b3%b5%ec%a7%80%ec%82%ac%ed%95%ad/?term_id&slug=5282",
      "author": null,
      "title": "[졸업]2024-1학기 졸업 대체 자격증 및 졸업 논문 계획서 제출 안내",
      "description": null,
      "category": [],
      "created_at": "2024-03-20T00:00:00+09:00",
      "updated_at": null,
      "thumbnail": null,
      "content": "\n\t\t\t\t\t\t<p>2024-1학기 졸업 예정자분들은 기한 내 졸업 대체 자격증 혹은 졸업논문을 제출하여 주시기 바랍니다.</p>\n<p>&nbsp;</p>\n<p>졸업 대체 자격증</p>\n<p>-JPT 700점 이상(제출일 기준으로 2년내 취득분만 유효) 혹은 JLPT N1 이상(점수가 표기되어 있어야 함.)</p>\n<p><span style=\"color: #000000\">-제출기한은 5월 말</span>까지 이며, 스캔하여 학번, 성함과 함께 학과 이메일(japanstu@ssu.ac.kr)로 제출</p>\n<p>&nbsp;</p>\n<p>졸업논문</p>\n<p>-4/12(금)까지 졸업논문계획서를 지도교수님과 논의 후 작성하여 학과 사무실로 직접 제출</p>\n<p>-논문완본은 5월 말까지 제본하여 3부를 학과 사무실로 직접 제출</p>\n<p>-졸업논문계획서 및 졸업논문 양식은 첨부파일 확인</p>\n<p>&nbsp;</p>\n<p>기타 문의사항은 학과홈페이지 졸업요건 메뉴 혹은 학과사무실(02-820-0530)로 문의</p>\n\t\t\t\t\t",
      "attachments": [],
      "metadata": null
    },
    {
      "id": "5286",
      "url": "https://japanstu.ssu.ac.kr/%ed%95%99%ea%b3%bc%ec%82%ac%eb%ac%b4%ec%8b%a4%ec%95%8c%eb%a6%bc/%ea%b3%b5%ec%a7%80%ec%82%ac%ed%95%ad/?term_id&slug=5286",
      "author": null,
      "title": "[안내]2024학년도 국가우수장학금(인문100년, 예술체육비전) 신규장학생 사전신청 안내(~4/5까지)",
      "description": null,
      "category": [],
      "created_at": "2024-03-20T00:00:00+09:00",
      "updated_at": null,
      "thumbnail": null,
      "content": "\n\t\t\t\t\t\t<p class=\"0\">가.&nbsp;장학금명 및 지원대상</p>\n<table>\n<tbody>\n<tr>\n<td valign=\"middle\">\n<p class=\"0\">장학금명</p>\n</td>\n<td valign=\"middle\">\n<p class=\"0\">유형</p>\n</td>\n<td valign=\"middle\">\n<p class=\"0\">지원기간</p>\n</td>\n<td valign=\"middle\">\n<p class=\"0\">지원대상</p>\n</td>\n</tr>\n<tr>\n<td rowspan=\"2\" valign=\"middle\">\n<p class=\"0\">인문</p>\n<p class=\"0\">100년</p>\n</td>\n<td valign=\"middle\">\n<p class=\"0\">전공탐색</p>\n</td>\n<td valign=\"middle\">\n<p class=\"0\">정규학기 내 최대</p>\n<p class=\"0\">8학기</p>\n</td>\n<td valign=\"middle\">\n<p class=\"0\">인문사회계열 학과(부)</p>\n<p class=\"0\">2024학년도 신입생</p>\n</td>\n</tr>\n<tr>\n<td valign=\"middle\">\n<p class=\"0\">전공확립</p>\n</td>\n<td valign=\"middle\">\n<p class=\"0\">정규학기 내 최대</p>\n<p class=\"0\">4학기</p>\n</td>\n<td valign=\"middle\">\n<p class=\"0\">인문사회계열 학과(부)</p>\n<p class=\"0\">3학년&nbsp;1학기 재학생</p>\n</td>\n</tr>\n<tr>\n<td rowspan=\"2\" valign=\"middle\">\n<p class=\"0\">예술체육</p>\n<p class=\"0\">비전</p>\n</td>\n<td valign=\"middle\">\n<p class=\"0\">전공탐색</p>\n</td>\n<td valign=\"middle\">\n<p class=\"0\">정규학기 내 최대</p>\n<p class=\"0\">8학기</p>\n</td>\n<td valign=\"middle\">\n<p class=\"0\">예술 및 체육계열 학과(부)</p>\n<p class=\"0\">2024학년도 신입생</p>\n</td>\n</tr>\n<tr>\n<td valign=\"middle\">\n<p class=\"0\">전공확립</p>\n</td>\n<td valign=\"middle\">\n<p class=\"0\">정규학기 내 최대</p>\n<p class=\"0\">4학기</p>\n</td>\n<td valign=\"middle\">\n<p class=\"0\">예술 및 체육계열 학과(부)</p>\n<p class=\"0\">3학년&nbsp;1학기 재학생</p>\n</td>\n</tr>\n</tbody>\n</table>\n<p class=\"0\">&nbsp;나.&nbsp;지원내용</p>\n<p class=\"0\">&nbsp; 1)&nbsp;Ⅰ유형:&nbsp;등록금 전액,&nbsp;생활비 학기당&nbsp;250만원</p>\n<p class=\"0\">&nbsp; 2)&nbsp;Ⅱ유형:&nbsp;등록금 전액</p>\n<p class=\"0\">&nbsp; ※&nbsp;기초생활수급자의 경우 유형에 상관없이 생활비 학기당&nbsp;250만원 추가 지원</p>\n<p class=\"0\">\n</p><p class=\"0\">3.&nbsp;학생 사전 신청기간:&nbsp;2024.03.19.(화) 09:00 ~ 2024.04.05.(금) 18:00&nbsp;까지</p>\n<p class=\"0\">※&nbsp;온라인 사전 신청을 우선적으로 진행하며,&nbsp;배정인원 확정 후 추가 서류제출 및 심사 관련</p>\n<p class=\"0\">&nbsp; 사항 추후 별도 안내</p>\n<p class=\"0\">※&nbsp;신청방법:&nbsp;붙임 매뉴얼 참고</p>\n<p class=\"0\">\n</p><p class=\"0\">4.&nbsp;선발 일정</p>\n<p class=\"0\">&nbsp;가. [학생]&nbsp;희망자 한국장학재단 홈페이지에서 사전신청</p>\n<p class=\"0\">&nbsp;나. [대학]&nbsp;대학별 자체 선발 및 재단 추천</p>\n<p class=\"0\">&nbsp;&nbsp;<u>※&nbsp;</u><u>4~5월중 각 대학으로 신규장학생 추천 공문 발송 예정</u></p>\n<p class=\"0\">&nbsp;다. [재단]&nbsp;장학생 최종 선정</p>\n\t\t\t\t\t",
      "attachments": [],
      "metadata": null
    },
    {
      "id": "5275",
      "url": "https://japanstu.ssu.ac.kr/%ed%95%99%ea%b3%bc%ec%82%ac%eb%ac%b4%ec%8b%a4%ec%95%8c%eb%a6%bc/%ea%b3%b5%ec%a7%80%ec%82%ac%ed%95%ad/?term_id&slug=5275",
      "author": null,
      "title": "[안내]2024학년도 1학기 학과근로 장학생 선발 시행 안내",
      "description": null,
      "category": [],
      "created_at": "2024-01-31T00:00:00+09:00",
      "updated_at": null,
      "thumbnail": null,
      "content": "\n\t\t\t\t\t\t<p>1. 학과근로장학생 자격 및 선발기준</p>\n<p>가. 2024학년도 1학기 국가장학금을&nbsp;<strong><u>1차</u></strong>&nbsp;신청하고 소득분위가 8분위 이내인 자</p>\n<p>※ 국가장학금을 신청할 수 없는 대한민국 국적 미소지자도 선발 가능</p>\n<p>(단, 순수외국인전형으로 입학한 외국인 유학생은 선발 불가)</p>\n<p>나. 2024학년도 1학기 재학 및 복학예정자로 해당학기 등록금 납부 예정인 자</p>\n<p>1) 2024학년도 1학기 전 등록휴학 후 복학시 선발 불가(등록대체자)</p>\n<p>2) 학기 중 미등록, 입학취소, 복학취소 등으로 인한 학적변동시 모든 장학금 취소</p>\n<p>3) 2024학년도 1학기 기준 이수학기가&nbsp;<u>2~8학기</u>만 가능(1학기 신청 불가, 건축학&nbsp;전공자의 경우 10학기까지)</p>\n<p>다. 직전학기 취득학점 및 학업성적 제한 없음</p>\n<p>라. 장애인, 북한이탈주민 및 자립준비청년 우선 선발 (한국장학재단 정보 활용)</p>\n<p>마. 타 장학금과 중복수혜 가능(근로장학금 간 중복 불가)</p>\n<p>※ 본 장학금은 학업장려비 지원 목적으로 등록금(입학금 및 수업료)를 초과하여 지급</p>\n<p>바. 학과별 배정인원 내에서 학과근로A 또는 B 타입 학과 자율선발 가능</p>\n<p>(예: 학과근로B 2명 = 학과근로A 1명)</p>\n<p>사. 국가근로장학생 및 교내근로장학생에 선발되지 않은 자</p>\n<p>&nbsp;</p>\n<p>2. 유의사항</p>\n<p>가. 선발된 학생은 소속부서에서 지정된 근로시간 동안 근무해야 하며, 학기 중 학적변동</p>\n<p>등 불가피한 사유가 인정되는 중도 포기 시 근로한 시간만 장학금 지급</p>\n<p>나. 2024년 7월 근로평가 전까지 교체 가능 (단, 교체 전 학생의 근로시간을 차감)</p>\n<p><b><u>※근로 중도 교체 및 중단 시 장학팀으로 공문 요망</u></b></p>\n<p>다. 교체 전·후 학생 모두 근로평가 실시</p>\n<p>&nbsp;</p>\n<p>3. 예산사항</p>\n<p>가. 시간당 장학금액을 9,860원으로 책정</p>\n<table border=\"1\" cellpadding=\"0\" cellspacing=\"0\">\n<tbody>\n<tr>\n<td>&nbsp;장학금명</td>\n<td>시간당<p></p>\n<p>장학금액</p></td>\n<td>총 근로시간(학기)</td>\n<td>1인당<p></p>\n<p>장학금액(원)</p></td>\n<td>인원(명)</td>\n<td>합계(원)</td>\n</tr>\n<tr>\n<td>학과근로A</td>\n<td>9,860원</td>\n<td>10시간*20주=200시간</td>\n<td>1,972,000</td>\n<td>198</td>\n<td>390,456,000</td>\n</tr>\n<tr>\n<td>학과근로B</td>\n<td>&nbsp;9,860원</td>\n<td>&nbsp;5시간*20주=100시간</td>\n<td>986,000</td>\n<td>0</td>\n<td>0</td>\n</tr>\n<tr>\n<td colspan=\"4\">&nbsp;총계</td>\n<td>&nbsp;&nbsp;198</td>\n<td>390,456,000</td>\n</tr>\n</tbody>\n</table>\n<p>※ 국제무역학과, 금융경제학과, 미디어경영학과&nbsp;배정인원(학과 자체 예산) 미반영</p>\n<p>나.&nbsp;학과근로 A유형을&nbsp;기준으로 배정하며,&nbsp;<strong>학과별로 A:B=1:2 비율로 조정 가능</strong></p>\n<p>다. 재원: 교내장학금_학부 / 기타장학</p>\n<p>라. 지급일정:&nbsp;매월 셋째주 금요일</p>\n<p>&nbsp;</p>\n<p>5. 행정사항</p>\n<p>가. 선발공고: 2024년 1월 29일(월)</p>\n<p>나. 학생신청방법: u-SAINT포털→등록/장학→근로장학금 신청→지원서 출력/제출</p>\n<p>다. 온라인신청 및 서류제출기간: <span style=\"color: #ff0000\"><strong>2024년 1월 30일(화) 10:00 ~ 2월 7일(수) 17:00</strong></span></p>\n<p>1) 제출서류: <span style=\"color: #ff0000\"><strong>지원서 (u-SAINT 출력본,&nbsp;본인서명 필수)</strong></span></p>\n<p><span style=\"color: #000000\">2) 선발인원: 학과근로A 3명</span></p>\n<p>2) 제출장소: 교내근로(장학팀), 학과근로 (각 학과사무실)</p>\n<p>라. 교내 및 학과근로장학생 최종선발 및 발표: 2024. 2. 22(목) 18:00 예정</p>\n\t\t\t\t\t",
      "attachments": [],
      "metadata": null
    },
    {
      "id": "5266",
      "url": "https://japanstu.ssu.ac.kr/%ed%95%99%ea%b3%bc%ec%82%ac%eb%ac%b4%ec%8b%a4%ec%95%8c%eb%a6%bc/%ea%b3%b5%ec%a7%80%ec%82%ac%ed%95%ad/?term_id&slug=5266",
      "author": null,
      "title": "2024학년도 1학기 백마성적우수장학금 선발기준 안내",
      "description": null,
      "category": [],
      "created_at": "2024-01-17T00:00:00+09:00",
      "updated_at": null,
      "thumbnail": null,
      "content": "\n\t\t\t\t\t\t<p>자격요건</p>\n<p>가. 2024학년도 1학기 국가장학금을 신청하여 소득분위 조회가 가능한 자</p>\n<p>1) 1차 신청자에 한하여 등록금고지서 사전감면</p>\n<p>2) 1차 미신청자 : 2차 신청/서류제출 확인 후 지급</p>\n<p>(2차 신청자도 선발 및 사후지급가능하므로 학과에서는 현재 미신청자도 선발 요망)</p>\n<p>3) 국가장학금을 신청할 수 없는 대한민국 국적 미소지자도 선발 가능</p>\n<p>(단, 순수외국인전형으로 입학한 외국인유학생은 선발 불가)</p>\n<p>&nbsp;</p>\n<p>나. 2024학년도 1학기 재학 및 복학예정자로 해당학기 등록금 납부 예정인 자</p>\n<p>1) 2024학년도 1학기 前등록휴학 후 복학시 선발대상에서 제외(등록대체자)</p>\n<p>2) 학기 중 미등록, 입학취소, 복학취소 등으로 인한 학적변동시 모든 장학금 취소</p>\n<p>3) 선발 후, 학기 중 휴학 시 백마성적우수장학금은 복학학기로 이월</p>\n<p>※ 추가 또는 교체선발 시 재학 중인 학생만 선발 (휴학생에 대한 추가/교체 불가)</p>\n<p>&nbsp;</p>\n<p>다. 직전학기 15학점 이상 이수한 자 (졸업 직전학기는 직전학기 12학점 이상)</p>\n<p>&nbsp;</p>\n<p>라. 정규등록학기가 8학기 이내인 자(건축학과 건축학전공: 정규등록 10학기 이내인 자)</p>\n<p>&nbsp;</p>\n<p>마. F학점 포함 학적부성적 기준 직전학기 3.5 이상인 자</p>\n<p>&nbsp;</p>\n<p>바. 모든 교내장학금간 중복수혜 불가</p>\n<p>1) 신청장학금 중 수혜금액이 큰 장학금 자동선발</p>\n<p>2) 중복수혜 가능 장학금: 국가장학금, 교외장학금, 학과우수장학금, 기타 학업장려비 지원 목적 장학금 등</p>\n<p>&nbsp;</p>\n<p>사. 졸업예정자 선발 불가(조기졸업 대상자 포함)하므로 유의</p>\n<p>&nbsp;</p>\n<p>또한 다음과 같은 학과 내규에 따라 장학금이 지급되오니 참고하시기 바랍니다.</p>\n<p>1) 1학년 재학생은 전공기초와 전공선택 과목을 전부 이수해야 함.</p>\n<p>2) 2,3학년 재학생은 전공선택 3과목 이상 이수해야 함.</p>\n<p>3) 4학년 재학생은 전공선택 2과목 이상 이수해야 함.</p>\n<p>4) 전과를 신청한 학생은 백마 성적 장학금 선발 대상에서 제외됨.</p>\n<p>&nbsp;</p>\n<p style=\"text-align: center\">2024.01.17</p>\n<p style=\"text-align: center\">일어일문학과</p>\n\t\t\t\t\t",
      "attachments": [],
      "metadata": null
    },
    {
      "id": "5268",
      "url": "https://japanstu.ssu.ac.kr/%ed%95%99%ea%b3%bc%ec%82%ac%eb%ac%b4%ec%8b%a4%ec%95%8c%eb%a6%bc/%ea%b3%b5%ec%a7%80%ec%82%ac%ed%95%ad/?term_id&slug=5268",
      "author": null,
      "title": "[일어일문학과]일어일문학과 내규(2024.01.17. 수정)",
      "description": null,
      "category": [
        "공지"
      ],
      "created_at": "2024-01-17T00:00:00+09:00",
      "updated_at": null,
      "thumbnail": null,
      "content": "\n\t\t\t\t\t\t<ol>\n<li><strong>수강신청 건</strong></li>\n</ol>\n<p>&nbsp;</p>\n<p>1) 3학년은 1학년 수업 수강 불가</p>\n<p>2) 4학년은 1,2학년 수업 수강 불가</p>\n<p>&nbsp;</p>\n<p>단, 편입생 및 전과생인 경우 1학년 전공기초 수업이나 2학년 과목을 이수 시에 학과장님의 승인을 조건으로 수강 가능하다.</p>\n<p>&nbsp;</p>\n<p>&nbsp;</p>\n<ol start=\"2\">\n<li><strong>장학금 신청 건</strong></li>\n</ol>\n<p>&nbsp;</p>\n<p>1) 1학년 재학생은 전공기초와 전공선택과목을 전부 이수해야 함.</p>\n<p>2) 2,3학년 재학생은 전공선택 3과목 이상 이수해야 함.</p>\n<p>3) 4학년 재학생은 전공선택 2과목 이상 이수해야 함.</p>\n<p>4) 전과를 신청한 학생은 백마 성적 장학금 선발 대상에서 제외됨.</p>\n<p>&nbsp;</p>\n<p>&nbsp;</p>\n<ol start=\"3\">\n<li><strong>교환학생 학점인정 건</strong></li>\n</ol>\n<p>&nbsp;</p>\n<p>1) 단일전공자인 경우 일어일문학과 과목 최대 9학점 까지 인정.</p>\n<p>2) 타학과 복수전공자 및 부전공자인 경우 일어일문학과 최대 6학점 까지 인정.</p>\n<p>&nbsp;</p>\n<p>&nbsp;</p>\n<p>&nbsp;</p>\n<p style=\"text-align: center\"><span style=\"font-size: 14pt\">일어일문학과</span></p>\n<p style=\"text-align: center\"><span style=\"font-size: 14pt\">2024.01.17</span></p>\n\t\t\t\t\t",
      "attachments": [],
      "metadata": null
    },
    {
      "id": "5201",
      "url": "https://japanstu.ssu.ac.kr/%ed%95%99%ea%b3%bc%ec%82%ac%eb%ac%b4%ec%8b%a4%ec%95%8c%eb%a6%bc/%ea%b3%b5%ec%a7%80%ec%82%ac%ed%95%ad/?term_id&slug=5201",
      "author": null,
      "title": "[안내]2023년도 교직과정 이수 신청 안내(~12/8)",
      "description": null,
      "category": [],
      "created_at": "2023-10-12T00:00:00+09:00",
      "updated_at": null,
      "thumbnail": null,
      "content": "\n\t\t\t\t\t\t<p class=\"0\">1.&nbsp;교직이수&nbsp;신청기한:&nbsp;2023.&nbsp;12. 8.(금) 17:00 까지</p>\n<p>&nbsp;</p>\n<p class=\"0\"><b>2.&nbsp;신청대상</b><b>:</b>&nbsp;교직 설치학과(부)&nbsp;소속&nbsp;2학년&nbsp;(3학기 혹은&nbsp;4학기)&nbsp;재학생 및 휴학생</p>\n<table>\n<tbody>\n<tr class=\"xfeDeleteRow\">\n<td style=\"text-align: center\" valign=\"middle\">\n<p class=\"0\"><b>’23-2학기 기준 학적</b></p>\n</td>\n<td style=\"text-align: center\" valign=\"middle\">\n<p class=\"0\">&nbsp;신청가능 여부</p>\n</td>\n</tr>\n<tr class=\"xfeDeleteRow\">\n<td style=\"text-align: center\" valign=\"middle\">\n<p class=\"0\">&nbsp;2학년&nbsp;1학기(3학기)&nbsp;재학</p>\n</td>\n<td rowspan=\"3\" style=\"text-align: center\" valign=\"middle\">\n<p class=\"0\">신청 가능</p>\n</td>\n</tr>\n<tr class=\"xfeDeleteRow\">\n<td style=\"text-align: center\" valign=\"middle\">\n<p class=\"0\">&nbsp;2학년&nbsp;1학기(3학기)&nbsp;이수 후 휴학</p>\n</td>\n</tr>\n<tr class=\"xfeDeleteRow\">\n<td style=\"text-align: center\" valign=\"middle\">\n<p class=\"0\">&nbsp;2학년&nbsp;2학기(4학기)&nbsp;재학</p>\n</td>\n</tr>\n<tr class=\"xfeDeleteRow\">\n<td style=\"text-align: center\" valign=\"middle\">\n<p class=\"0\">&nbsp;2학년&nbsp;2학기(4학기)&nbsp;이수 후 휴학</p>\n</td>\n<td style=\"text-align: center\" valign=\"middle\">\n<p class=\"0\">신청&nbsp;불가</p>\n</td>\n</tr>\n</tbody>\n</table>\n<p class=\"0\">&nbsp;※&nbsp;4학기 이수 후 휴학 중인 학생은 신청 불가능</p>\n<p>&nbsp;</p>\n<p class=\"0\"><b>3.&nbsp;교직 설치 학과(부)별 선발 인원</b></p>\n<table>\n<tbody>\n<tr>\n<td style=\"text-align: center\" valign=\"middle\">&nbsp;대학</td>\n<td style=\"text-align: center\" valign=\"middle\">학과(부)</td>\n<td style=\"text-align: center\" valign=\"middle\">표시과목</td>\n<td style=\"text-align: center\" valign=\"middle\">선발인원(명)</td>\n</tr>\n<tr>\n<td rowspan=\"6\" style=\"text-align: center\" valign=\"middle\">인문대학</td>\n<td style=\"text-align: center\" valign=\"middle\">국어국문학과</td>\n<td style=\"text-align: center\" valign=\"middle\">국어</td>\n<td style=\"text-align: center\" valign=\"middle\">3</td>\n</tr>\n<tr>\n<td style=\"text-align: center\" valign=\"middle\">영어영문학과</td>\n<td style=\"text-align: center\" valign=\"middle\">영어</td>\n<td style=\"text-align: center\" valign=\"middle\">7</td>\n</tr>\n<tr>\n<td style=\"text-align: center\" valign=\"middle\">중어중문학과</td>\n<td style=\"text-align: center\" valign=\"middle\">중국어</td>\n<td style=\"text-align: center\" valign=\"middle\">2</td>\n</tr>\n<tr>\n<td style=\"text-align: center\" valign=\"middle\">일어일문학과</td>\n<td style=\"text-align: center\" valign=\"middle\">일본어</td>\n<td style=\"text-align: center\" valign=\"middle\">3</td>\n</tr>\n<tr>\n<td style=\"text-align: center\" valign=\"middle\">철학과</td>\n<td style=\"text-align: center\" valign=\"middle\">철학</td>\n<td style=\"text-align: center\" valign=\"middle\">2</td>\n</tr>\n<tr>\n<td style=\"text-align: center\" valign=\"middle\">사학과</td>\n<td style=\"text-align: center\" valign=\"middle\">역사</td>\n<td style=\"text-align: center\" valign=\"middle\">3</td>\n</tr>\n<tr>\n<td rowspan=\"3\" style=\"text-align: center\" valign=\"middle\">자연과학대학</td>\n<td style=\"text-align: center\" valign=\"middle\">수학과</td>\n<td style=\"text-align: center\" valign=\"middle\">수학</td>\n<td style=\"text-align: center\" valign=\"middle\">3</td>\n</tr>\n<tr>\n<td style=\"text-align: center\" valign=\"middle\">물리학과</td>\n<td style=\"text-align: center\" valign=\"middle\">물리</td>\n<td style=\"text-align: center\" valign=\"middle\">4</td>\n</tr>\n<tr>\n<td style=\"text-align: center\" valign=\"middle\">화학과</td>\n<td style=\"text-align: center\" valign=\"middle\">화학</td>\n<td style=\"text-align: center\" valign=\"middle\">4</td>\n</tr>\n<tr>\n<td rowspan=\"2\" style=\"text-align: center\" valign=\"middle\">경제통상대학</td>\n<td style=\"text-align: center\" valign=\"middle\">경제학과</td>\n<td style=\"text-align: center\" valign=\"middle\">일반사회</td>\n<td style=\"text-align: center\" valign=\"middle\">3</td>\n</tr>\n<tr>\n<td style=\"text-align: center\" valign=\"middle\">글로벌통상학과</td>\n<td style=\"text-align: center\" valign=\"middle\">상업</td>\n<td style=\"text-align: center\" valign=\"middle\">5</td>\n</tr>\n<tr>\n<td rowspan=\"2\" style=\"text-align: center\" valign=\"middle\">경영대학</td>\n<td style=\"text-align: center\" valign=\"middle\">경영학부</td>\n<td style=\"text-align: center\" valign=\"middle\">상업</td>\n<td style=\"text-align: center\" valign=\"middle\">8</td>\n</tr>\n<tr>\n<td style=\"text-align: center\" valign=\"middle\">회계학과</td>\n<td style=\"text-align: center\" valign=\"middle\">상업</td>\n<td style=\"text-align: center\" valign=\"middle\">2</td>\n</tr>\n<tr>\n<td rowspan=\"2\" style=\"text-align: center\" valign=\"middle\">공과대학</td>\n<td style=\"text-align: center\" valign=\"middle\">화학공학과</td>\n<td style=\"text-align: center\" valign=\"middle\">화공</td>\n<td style=\"text-align: center\" valign=\"middle\">3</td>\n</tr>\n<tr>\n<td style=\"text-align: center\" valign=\"middle\">전기공학부</td>\n<td style=\"text-align: center\" valign=\"middle\">전기</td>\n<td style=\"text-align: center\" valign=\"middle\">6</td>\n</tr>\n<tr>\n<td rowspan=\"5\" style=\"text-align: center\" valign=\"middle\">IT대학</td>\n<td rowspan=\"2\" style=\"text-align: center\" valign=\"middle\">전자정보공학부<p></p>\n<p>전자공학전공</p></td>\n<td style=\"text-align: center\" valign=\"middle\">전자</td>\n<td rowspan=\"2\" style=\"text-align: center\" valign=\"middle\">4</td>\n</tr>\n<tr>\n<td style=\"text-align: center\" valign=\"middle\">통신</td>\n</tr>\n<tr>\n<td rowspan=\"2\" style=\"text-align: center\" valign=\"middle\">전자정보공학부<p></p>\n<p>IT융합전공</p></td>\n<td style=\"text-align: center\" valign=\"middle\">전자</td>\n<td rowspan=\"2\" style=\"text-align: center\" valign=\"middle\">4</td>\n</tr>\n<tr>\n<td style=\"text-align: center\" valign=\"middle\">통신</td>\n</tr>\n<tr>\n<td style=\"text-align: center\" valign=\"middle\">컴퓨터학부</td>\n<td style=\"text-align: center\" valign=\"middle\">정보·컴퓨터</td>\n<td style=\"text-align: center\" valign=\"middle\">7</td>\n</tr>\n<tr>\n<td colspan=\"3\" style=\"text-align: center\" valign=\"middle\">&nbsp;계</td>\n<td style=\"text-align: center\" valign=\"middle\">73</td>\n</tr>\n</tbody>\n</table>\n<div class=\"hwp_editor_board_content\" id=\"hwpEditorBoardContent\"></div>\n<p class=\"0\">\n</p><p class=\"0\"><b>4. 학교 홈페이지 공지사항&nbsp;</b><b>바로보기</b>&nbsp;☞<span style=\"color: #393939\">&nbsp;</span><b><u></u></b><a href=\"https://scatch.ssu.ac.kr/%ea%b3%b5%ec%a7%80%ec%82%ac%ed%95%ad/?f&amp;category=%EA%B5%90%EC%A7%81&amp;slug=2023%ED%95%99%EB%85%84%EB%8F%84-%EA%B5%90%EC%A7%81%EA%B3%BC%EC%A0%95-%EC%9D%B4%EC%88%98-%EC%8B%A0%EC%B2%AD-%EC%95%88%EB%82%B4&amp;keyword\" rel=\"noopener\" target=\"_blank\"><span style=\"color: #0000ff\"><b><u>교직과정 이수신청 안내</u></b></span><span style=\"color: #393939\">.</span></a></p>\n\t\t\t\t\t",
      "attachments": [],
      "metadata": null
    },
    {
      "id": "5210",
      "url": "https://japanstu.ssu.ac.kr/%ed%95%99%ea%b3%bc%ec%82%ac%eb%ac%b4%ec%8b%a4%ec%95%8c%eb%a6%bc/%ea%b3%b5%ec%a7%80%ec%82%ac%ed%95%ad/?term_id&slug=5210",
      "author": null,
      "title": "[안내]2023년 특별상환유예 제도 안내",
      "description": null,
      "category": [],
      "created_at": "2023-10-12T00:00:00+09:00",
      "updated_at": null,
      "thumbnail": null,
      "content": "\n\t\t\t\t\t\t<p style=\"text-align: center\">– 일반상환학자금대출 상환 부담을 덜어주는 –</p>\n<p style=\"text-align: center\"><b>≪ </b><b>특별상환 유예대출 신청 안내 </b><b>≫</b></p>\n<p>&nbsp;</p>\n<p>◆ <b>특별상환 유예대출이란</b><b>?</b></p>\n<ul>\n<li>경제적으로 곤란한 사유가 발생한 <b>일반상환학자금대출자의 원리금 상환을 최대 </b><b>3</b><b>년 간 유예해주는 제도</b>로 해당 금액은 별도 대출로 구성되어 <b>무이자 분할상환</b><b>(4</b><b>년 간</b><b>) </b><b>또는 만기 일시상환</b><b>(4</b><b>년 후</b><b>)</b> 하는 제도</li>\n</ul>\n<p>&nbsp;</p>\n<p>◆ <b>신청 기본 요건은</b><b>?</b></p>\n<ul>\n<li>만 35세 이하의 학부 또는 대학원 졸업생(대학원 재학생 가능)</li>\n<li>일반상환학자금대출 잔액 보유자(부실채권 미보유자)</li>\n<li>취업 후 상환 학자금 의무상환 개시 결정 전인 자</li>\n</ul>\n<p>&nbsp;</p>\n<p>◆ <b>추가 자격 요건은</b><b>?</b></p>\n<p>▷ 아래 요건 중 하나에 해당되면 신청 가능</p>\n<ul>\n<li>부모의 사망(신청일 기준 2년 이내)</li>\n<li>부모의 파산·면책 또는 개인회생 결정(신청일 기준 5년 이내)</li>\n<li>본인이 수급자·차상위 계층 또는 장애</li>\n<li>본인 또는 부모의 중증질병</li>\n<li>졸업 후 2년 이내 기한이익상실 예정자(연체 6개월)</li>\n<li>보이스 피싱, 불법사금융 피해에 처한 자(신청일 기준 2년 이내)</li>\n<li>고용 및 산업위기지역 거주 또는 실직·폐업자</li>\n<li>군복무(예정)자 중 연체 3개월 이상자(졸업여부 무관)</li>\n<li>대학생 창업자(정부·지자체 등 창업 지원 프로그램 참여자 포함, 졸업여부 무관)</li>\n<li>본인 또는 부모의 실직·폐업</li>\n</ul>\n<p>&nbsp;</p>\n<p><b>◆ </b><b>신청 방법 및 기간은</b><b>?</b></p>\n<ul>\n<li>한국장학재단 홈페이지 또는 모바일 앱에서 연간 상시 신청 가능</li>\n</ul>\n<p>&nbsp;</p>\n<p><b>◆ </b><b>상담 문의</b></p>\n<ul>\n<li>한국장학재단 대표 콜센터(☎1599-2000)</li>\n</ul>\n\t\t\t\t\t",
      "attachments": [],
      "metadata": null
    },
    {
      "id": "5185",
      "url": "https://japanstu.ssu.ac.kr/%ed%95%99%ea%b3%bc%ec%82%ac%eb%ac%b4%ec%8b%a4%ec%95%8c%eb%a6%bc/%ea%b3%b5%ec%a7%80%ec%82%ac%ed%95%ad/?term_id&slug=5185",
      "author": null,
      "title": "[졸업]2023-2학기 졸업 대체 자격증 및 졸업 논문 계획서 제출 안내",
      "description": null,
      "category": [],
      "created_at": "2023-09-15T00:00:00+09:00",
      "updated_at": null,
      "thumbnail": null,
      "content": "\n\t\t\t\t\t\t<p>2023-2학기 졸업 예정자분들은 기한 내 졸업 대체 자격증 혹은 졸업논문을 제출하여 주시기 바랍니다.</p>\n<p>&nbsp;</p>\n<p>졸업 대체 자격증</p>\n<p>-JPT 700점 이상(제출일 기준으로 2년내 취득분만 유효) 혹은 JLPT N1 이상(점수가 표기되어 있어야 함.)</p>\n<p><span style=\"color: #000000\">-제출기한은 11월 말</span>까지 이며, 스캔하여 학번, 성함과 함께 학과 이메일(japanstu@ssu.ac.kr)로 제출</p>\n<p>&nbsp;</p>\n<p>졸업논문</p>\n<p>-10/13(금)까지 졸업논문계획서를 지도교수님과 논의 후 작성하여 학과 사무실로 직접 제출</p>\n<p>-논문완본은 11월 말까지 제본하여 3부를 학과 사무실로 직접 제출</p>\n<p>-졸업논문계획서 및 졸업논문 양식은 첨부파일 확인</p>\n<p>&nbsp;</p>\n<p>기타 문의사항은 학과홈페이지 졸업요건 메뉴 혹은 학과사무실(02-820-0530)로 문의</p>\n\t\t\t\t\t",
      "attachments": [],
      "metadata": null
    },
    {
      "id": "5179",
      "url": "https://japanstu.ssu.ac.kr/%ed%95%99%ea%b3%bc%ec%82%ac%eb%ac%b4%ec%8b%a4%ec%95%8c%eb%a6%bc/%ea%b3%b5%ec%a7%80%ec%82%ac%ed%95%ad/?term_id&slug=5179",
      "author": null,
      "title": "[안내]2023학년도 한나장학생 모집 안내(~9/18)",
      "description": null,
      "category": [],
      "created_at": "2023-09-08T00:00:00+09:00",
      "updated_at": null,
      "thumbnail": null,
      "content": "\n\t\t\t\t\t\t<p>2023학년도 한나장학생 모집 안내</p>\n<p>한나장학금은 우리 학과 겸임교수를 역임하신 김정희 교수님께서 출연해 주신 기금으로 운영하는 일어일문학과 내부 장학금입니다.</p>\n<p>조금이나마 학업 수행에 도움이 되었으면 합니다. 많은 지원 바랍니다.</p>\n<p>&nbsp;</p>\n<p>1, 대상: 일어일문학과 1학년</p>\n<p>2. 모집인원: 2명</p>\n<p>3.&nbsp; 구비서류: 자기소개서, 건강보험료 납입증명서, 주민등록등본 각 1부</p>\n<p>4. 신청기한: 9월 18일(월) 15시까지 학과사무실로 직접 제출 혹은 이메일(japanstu@ssu.ac.kr) 제출</p>\n<p>5. 장학금액: 1,000,000원(1인당)</p>\n<p>6. 지급시기: 10월 중 예정</p>\n<p>7. 기타 문의사항은 학과 사무실(02-820-0530)로 연락 바랍니다.</p>\n<p>&nbsp;</p>\n\t\t\t\t\t",
      "attachments": [],
      "metadata": null
    },
    {
      "id": "5173",
      "url": "https://japanstu.ssu.ac.kr/%ed%95%99%ea%b3%bc%ec%82%ac%eb%ac%b4%ec%8b%a4%ec%95%8c%eb%a6%bc/%ea%b3%b5%ec%a7%80%ec%82%ac%ed%95%ad/?term_id&slug=5173",
      "author": null,
      "title": "[안내]2023학년도 2학기 교내장학금 신청 안내(~9/15)",
      "description": null,
      "category": [],
      "created_at": "2023-09-06T00:00:00+09:00",
      "updated_at": null,
      "thumbnail": null,
      "content": "\n\t\t\t\t\t\t<p><strong>1. 교내장학금 자격요건</strong></p>\n<p>가. 2023학년도 2학기 국가장학금 신청 및 서류제출을 완료하고 소득분위가 조회된 자</p>\n<p>(국가장학금 지급 대상 분위의 경우 심사가 완료된 자)</p>\n<p>나. 2023학년도 2학기 재학 학생으로 등록금 납부 예정인 자</p>\n<p>1) 2023학년도 2학기 前 등록휴학 후 복학시 장학생 선발대상에서 제외</p>\n<p>2) 미등록, 입학취소, 복학취소, 휴학 등 학적변동 시 모든 장학금 취소</p>\n<p>다. 직전학기 15학점 이상 이수한 자(최종 직전학기는 12학점)</p>\n<p>라. 정규 등록학기가 8학기 이내인 자(건축학부 건축학전공은 10학기 이내)</p>\n<p>&nbsp;</p>\n<p><strong>2. 신청절차</strong></p>\n<p>가. 온라인 신청기간 및 서류제출기간 :&nbsp;~9월 15일(금)까지 예정 (추가 신청 없음)</p>\n<p>나. 학생 신청방법: u-SAINT포털 – 등록/장학 – 장학메뉴 – 장학금 신청</p>\n<p>다. 학생 서류제출: 온라인 신청기간 내 방문 및 등기우편제출 가능(세부내용 붙임 파일 참조)</p>\n<p>※ 단, 전문자격시험합격자장학금의 경우 등기우편 불가</p>\n\t\t\t\t\t",
      "attachments": [],
      "metadata": null
    },
    {
      "id": "5155",
      "url": "https://japanstu.ssu.ac.kr/%ed%95%99%ea%b3%bc%ec%82%ac%eb%ac%b4%ec%8b%a4%ec%95%8c%eb%a6%bc/%ea%b3%b5%ec%a7%80%ec%82%ac%ed%95%ad/?term_id&slug=5155",
      "author": null,
      "title": "[안내]2023학년도 2학기 한국장학재단 국가장학금 2차 신청 안내(~9/14)",
      "description": null,
      "category": [],
      "created_at": "2023-08-16T00:00:00+09:00",
      "updated_at": null,
      "thumbnail": null,
      "content": "\n\t\t\t\t\t\t<p><img alt=\"\" class=\"aligncenter size-full wp-image-5156\" height=\"7016\" sizes=\"(max-width: 4961px) 100vw, 4961px\" src=\"https://japanstu.ssu.ac.kr/wp-content/uploads/sites/119/2023/08/포스터-2023년-2학기-국가장학금-2차-신청.jpg\" srcset=\"https://japanstu.ssu.ac.kr/wp-content/uploads/sites/119/2023/08/포스터-2023년-2학기-국가장학금-2차-신청.jpg 4961w, https://japanstu.ssu.ac.kr/wp-content/uploads/sites/119/2023/08/포스터-2023년-2학기-국가장학금-2차-신청-212x300.jpg 212w, https://japanstu.ssu.ac.kr/wp-content/uploads/sites/119/2023/08/포스터-2023년-2학기-국가장학금-2차-신청-768x1086.jpg 768w, https://japanstu.ssu.ac.kr/wp-content/uploads/sites/119/2023/08/포스터-2023년-2학기-국가장학금-2차-신청-724x1024.jpg 724w\" width=\"4961\"></p>\n\t\t\t\t\t",
      "attachments": [],
      "metadata": null
    },
    {
      "id": "5138",
      "url": "https://japanstu.ssu.ac.kr/%ed%95%99%ea%b3%bc%ec%82%ac%eb%ac%b4%ec%8b%a4%ec%95%8c%eb%a6%bc/%ea%b3%b5%ec%a7%80%ec%82%ac%ed%95%ad/?term_id&slug=5138",
      "author": null,
      "title": "[안내]2023학년도 2학기 학과근로 장학생 선발 시행 안내",
      "description": null,
      "category": [],
      "created_at": "2023-07-31T00:00:00+09:00",
      "updated_at": null,
      "thumbnail": null,
      "content": "\n\t\t\t\t\t\t<p>1. 학과근로장학생 자격 및 선발기준</p>\n<p>가. 2023학년도 2학기 국가장학금을&nbsp;신청하고 소득분위가 8분위 이내인 자</p>\n<p>※ 국가장학금을 신청할 수 없는 대한민국 국적 미소지자도 선발 가능</p>\n<p>(단, 순수외국인전형으로 입학한 외국인 유학생은 선발 불가)</p>\n<p>나. 2023학년도 2학기 재학 및 복학예정자로 해당학기 등록금 납부 예정인 자</p>\n<p>1) 2023학년도 2학기 전 등록휴학 후 복학시 선발 불가(등록대체자)</p>\n<p>2) 학기 중 미등록, 입학취소, 복학취소 등으로 인한 학적변동시 모든 장학금 취소</p>\n<p>3) 2023학년도 2학기 기준 이수학기가 2~8학기만 가능</p>\n<p>다. 직전학기 취득학점 및 학업성적 제한 없음</p>\n<p>라. 장애인, 북한이탈주민 및 자립준비청년 우선 선발 요망 (증빙제출 필요)</p>\n<p>마. 타 장학금과 중복수혜 가능(근로장학금 간 중복 불가)</p>\n<p>※ 본 장학금은 학업장려비 지원 목적으로 등록금(입학금 및 수업료)를 초과하여 지급</p>\n<p>&nbsp;</p>\n<p>바. 국가근로장학생 및 교내근로장학생에 선발되지 않은 자</p>\n<p>&nbsp;</p>\n<p>2. 유의사항</p>\n<p>가. 선발된 학생은 소속부서에서 지정된 근로시간 동안 근무해야 하며, 학기 중 학적변동</p>\n<p>등 불가피한 사유가 인정되는 중도 포기 시 근로한 시간만 장학금 지급</p>\n<p>나. 2023년 12월 근로평가 전까지 교체 가능 (단, 교체 전 학생의 근로시간을 차감)</p>\n<p><b><u>※근로 중도 교체 및 중단 시 장학팀으로 공문 요망</u></b></p>\n<p>다. 교체 전·후 학생 모두 근로평가 실시</p>\n<p>&nbsp;</p>\n<p>3. 예산사항</p>\n<p>가. 시간당 장학금액을 9,620원으로 책정</p>\n<table border=\"1\" cellpadding=\"0\" cellspacing=\"0\">\n<tbody>\n<tr>\n<td>&nbsp;장학금명</td>\n<td>시간당<p></p>\n<p>장학금액</p></td>\n<td>총 근로시간(학기)</td>\n<td>1인당<p></p>\n<p>장학금액(원)</p></td>\n<td>인원(명)</td>\n<td>합계(원)</td>\n</tr>\n<tr>\n<td>학과근로A</td>\n<td>9,620원</td>\n<td>10시간*20주=200시간</td>\n<td>1,924,000</td>\n<td>199</td>\n<td>382,876,000</td>\n</tr>\n<tr>\n<td>학과근로B</td>\n<td>&nbsp;9,620원</td>\n<td>&nbsp;5시간*20주=100시간</td>\n<td>962,000</td>\n<td>0</td>\n<td>0</td>\n</tr>\n<tr>\n<td colspan=\"4\">&nbsp;총계</td>\n<td>&nbsp;&nbsp;202</td>\n<td>382,876,000</td>\n</tr>\n</tbody>\n</table>\n<p>※ 국제무역학과, 금융경제학과, 미디어경영학과&nbsp;배정인원(학과 자체 예산) 미반영</p>\n<p>나.&nbsp;학과근로 A유형을&nbsp;기준으로 배정하며,&nbsp;<strong>학과별로 A:B=1:2 비율로 조정 가능</strong></p>\n<p>다. 재원: 교내장학금_학부 / 기타장학</p>\n<p>라. 지급일정:&nbsp;매월 셋째주 금요일</p>\n<p>&nbsp;</p>\n<p>4. 행정사항</p>\n<p>가. 선발공고: 2023년 7월 31일(월)</p>\n<p>나. 학생신청방법: u-SAINT포털→등록/장학→근로장학금 신청→지원서 출력/제출</p>\n<p>다. 온라인신청 및 서류제출기간: <span style=\"color: #ff0000\"><strong>2023년 7월 31일(월) 10:00 ~ 8월 8일(화) 17:00</strong></span></p>\n<p>1) 제출서류: <span style=\"color: #ff0000\">지원서 (u-SAINT 출력본,&nbsp;<b>본인서명 필수</b>)</span></p>\n<p>2) 제출장소: 교내근로(장학팀), 학과근로 (각 학과사무실)</p>\n<p>라. 학과근로장학생 최종선발 및 발표: 2023. 8. 18(금) 18:00 예정</p>\n\t\t\t\t\t",
      "attachments": [],
      "metadata": null
    },
    {
      "id": "3394",
      "url": "https://japanstu.ssu.ac.kr/%ed%95%99%ea%b3%bc%ec%82%ac%eb%ac%b4%ec%8b%a4%ec%95%8c%eb%a6%bc/%ea%b3%b5%ec%a7%80%ec%82%ac%ed%95%ad/?term_id&slug=3394",
      "author": null,
      "title": "[졸업]일어일문학과 졸업요건(2021.07.21자 최신화)",
      "description": null,
      "category": [
        "공지"
      ],
      "created_at": "2021-07-21T00:00:00+09:00",
      "updated_at": null,
      "thumbnail": null,
      "content": "\n\t\t\t\t\t\t<p><strong>졸 업 요 건</strong></p>\n<p>1.어학자격증: JPT 700점 이상(2009년 입학생부터/이전 입학생은 650점 이상) 혹은 JLPT N1 이상</p>\n<p>&nbsp;</p>\n<p>2.졸업논문: 논문양식에 맞춰서 작성된 논문완본을 3부 사무실로 제출(소프트 제본)</p>\n<p>&nbsp;</p>\n<ul style=\"list-style-type: square\">\n<li>7학기째인 학생 중 어학 자격증 미소지자는 논문계획서를 개강 후 20일까지 반드시 제출할 것(학기 초에 메일로 공지함).</li>\n<li>논문계획서 양식은 첨부파일의 양식을 따르며, 임의의 변경은 불가능함.</li>\n<li>논문완본 제출은 8학기 11월말까지 (2월 졸업생), 5월말까지 제출(8월 졸업생). 어학자격증도 같은 기간내에 제출.</li>\n<li>제출 기한 이후에 제출할 경우, 학사일정에 따라 반영이 안되서 해당학기 졸업이 어려울 수 있으니 기간 준수 필요.</li>\n<li>논문완본 제출 이전에 반드시 논문계획서에 지도교수님 확인을 받아 사무실로 제출할 것.</li>\n<li>졸업논문양식은 첨부파일의 양식을 따르며, 형식의 변경은 불가능함. 반드시 양식에 따라 작성할 것.</li>\n<li>개인정보의 변경이 있을 경우 학사시스템에도 변경할 것. 변경되지 않을 경우 졸업을 포함한 연락이 누락될 수 있음.(전화번호/메일주소 확인)</li>\n<li>졸업이수구분은 수시로 확인하여 이상이 있을시 학과사무실에 문의바람(졸업논문 및 자격증 입력여부는 6월 중순/12월 중순경부터 반영됨)</li>\n</ul>\n<p>&nbsp;</p>\n<p>기타 졸업에 관한 문의 사항이 있을 시, 학과사무실(japanstu@ssu.ac.kr)로 문의주시기 바랍니다.(메일로 문의할 경우, 좀 더 원활한 답신이 가능)</p>\n<p>*학기가 시작하는 3월, 9월에 1차 졸업여부 확인을 위한 메일이 전송될 예정이며 4월, 10월 초순 경에 논문계획서 및 어학자격증 제출을에 대한 메일을 전송할예정입니다. 학사시스템(u-saint)에 입력된 메일주소를 확인해주시기 바랍니다.</p>\n<p>&nbsp;</p>\n<p>일어일문학과</p>\n\t\t\t\t\t",
      "attachments": [],
      "metadata": null
    },
    {
      "id": "3094",
      "url": "https://japanstu.ssu.ac.kr/%ed%95%99%ea%b3%bc%ec%82%ac%eb%ac%b4%ec%8b%a4%ec%95%8c%eb%a6%bc/%ea%b3%b5%ec%a7%80%ec%82%ac%ed%95%ad/?term_id&slug=3094",
      "author": null,
      "title": "[중요안내]일어일문학과 수강신청관련 학과내규1-전공교과목 수강인원",
      "description": null,
      "category": [
        "공지"
      ],
      "created_at": "2021-03-12T00:00:00+09:00",
      "updated_at": null,
      "thumbnail": null,
      "content": "\n\t\t\t\t\t\t<p>전공교과목 수강인원을 원칙적으로 아래와 같이 정한다.</p>\n<p>&nbsp;</p>\n<p>1학년 전공교과목 총원 40명</p>\n<p>2학년 전공교과목 총원 40명</p>\n<p>3학년 전공교과목 총원 35명</p>\n<p>4학년 전공교과목 총원 25명</p>\n<p>&nbsp;</p>\n<p>단, 부득이한 경우 담당교수님께 의논하고 담당교수님이 학과장교수님과 상의하여 결정한다.</p>\n\t\t\t\t\t",
      "attachments": [],
      "metadata": null
    },
    {
      "id": "3099",
      "url": "https://japanstu.ssu.ac.kr/%ed%95%99%ea%b3%bc%ec%82%ac%eb%ac%b4%ec%8b%a4%ec%95%8c%eb%a6%bc/%ea%b3%b5%ec%a7%80%ec%82%ac%ed%95%ad/?term_id&slug=3099",
      "author": null,
      "title": "[중요안내]일어일문학과 수강신청관련 학과내규2-수강신청",
      "description": null,
      "category": [
        "공지"
      ],
      "created_at": "2021-03-12T00:00:00+09:00",
      "updated_at": null,
      "thumbnail": null,
      "content": "\n\t\t\t\t\t\t<p>&lt;수강신청 관련 학과 내규&gt;</p>\n<p>&nbsp;</p>\n<p>4학년은 1학년과 2학년 전공교과목을 원칙적으로 수강할 수 없으며, 3학년은 1학년 전공교과목을 원칙적으로 수강할 수 없다.</p>\n<p>&nbsp;</p>\n<p>단, 부득이한 사정으로 수강하고자 하는 경우 학과장 교수님께 허락을 받아야 한다.</p>\n\t\t\t\t\t",
      "attachments": [],
      "metadata": null
    }
  ]
}